{
  "total": 118916,
  "data": [
    {
      "id_img": "Original_697755_crop2608_1447880419",
      "lik": "UTb0sGqADnbLiHq9qhRMRkSRiLND0Tk7ctN8tpraiid7o9UpJEmeskWAel+sKcE7TyqgDGaCzQsZXRAgIN7aXZVy4706IhQgSYlgwrgVRHU=",
      "thub": "UTb0sGqADnbLiHq9qhRMRkSRiLND0Tk7ctN8tpraiid7o9UpJEmeskWAel+sKcE7N7UKadH5Otc7uqkY3X2Fx5Vy4706IhQgSYlgwrgVRHU=",
      "albl": [
        "Girls",
        "Original"
      ],
      "norl": [
        "Blonde",
        "Tea Cup",
        "bow Clothing",
        "Shoe",
        "Blush"
      ],
      "spel": [
        "Girls Uniform",
        "Girls Hair Yellow",
        "Girls Eyes Red",
        "Girls Long Hair",
        "Girls Hats",
        "Girls Tie Bows"
      ],
      "i_top": 0,
      "i_newest": 0,
      "i_sgg": 0,
      "h_img": 1320,
      "w_img": 929,
      "date_img_modified": 1645540990730,
      "file_size": "153.25 Kb"
    },
    {
      "id_img": "Original_697512_crop2608_555709602",
      "lik": "UTb0sGqADnbLiHq9qhRMRkSRiLND0Tk7ctN8tpraiidQ/AdqB1Wug3PK1ShpBSOpr5lu5eidhIpMIXCyHOBA45Vy4706IhQgSYlgwrgVRHU=",
      "thub": "UTb0sGqADnbLiHq9qhRMRkSRiLND0Tk7ctN8tpraiidQ/AdqB1Wug3PK1ShpBSOpnz2+daVeZA6Md2vUyT0MD5Vy4706IhQgSYlgwrgVRHU=",
      "albl": [
        "Girls",
        "Original"
      ],
      "norl": [
        "Aqua Eyes",
        "Blonde",
        "Twintails",
        "bow Clothing"
      ],
      "spel": [
        "Girls Hair Orange",
        "Girls Long Hair",
        "Girls Smile",
        "Girls Tie Bows",
        "Girls Eyes Blue"
      ],
      "i_top": 0,
      "i_newest": 0,
      "i_sgg": 0,
      "h_img": 1853,
      "w_img": 1304,
      "date_img_modified": 1645540990360,
      "file_size": "248.38 Kb"
    },
    {
      "id_img": "Original_697424_crop2608_1372174096",
      "lik": "UTb0sGqADnbLiHq9qhRMRkSRiLND0Tk7ctN8tpraiidR5ib/2yg8VubxGKhkx6u5+LQwTHDS5rG16eyYR00KrpVy4706IhQgSYlgwrgVRHU=",
      "thub": "UTb0sGqADnbLiHq9qhRMRkSRiLND0Tk7ctN8tpraiidR5ib/2yg8VubxGKhkx6u5QbB3602v+9YONiZeoupJr5Vy4706IhQgSYlgwrgVRHU=",
      "albl": [
        "Girls",
        "Original"
      ],
      "norl": [
        "Halloween"
      ],
      "spel": [
        "Girls Hair Silver",
        "Girls Sharp Canine Tooth",
        "Girls Hair White",
        "Girls Horns",
        "Girls Eyes Brown",
        "Girls Long Hair",
        "Girls Cute Cool",
        "Girls Smile",
        "Girls Tie Bows",
        "Girls Witch"
      ],
      "i_top": 0,
      "i_newest": 0,
      "i_sgg": 0,
      "h_img": 1358,
      "w_img": 956,
      "date_img_modified": 1645540989393,
      "file_size": "172.10 Kb"
    },
    {
      "id_img": "Original_697424_crop2608_-844461227",
      "lik": "UTb0sGqADnbLiHq9qhRMRkSRiLND0Tk7ctN8tpraiidWTahWTzoKiZQljqybC8nJ2RElIHfh4rufjjfSEAM6wpVy4706IhQgSYlgwrgVRHU=",
      "thub": "UTb0sGqADnbLiHq9qhRMRkSRiLND0Tk7ctN8tpraiidWTahWTzoKiZQljqybC8nJRpzSCT5PVBddTR5XYyZ8Q5Vy4706IhQgSYlgwrgVRHU=",
      "albl": [
        "Girls",
        "Original"
      ],
      "norl": [
        "Halloween"
      ],
      "spel": [
        "Girls Eyes Brown",
        "Girls Long Hair",
        "Girls Hats",
        "Girls Smile",
        "Girls Tie Bows",
        "Girls Witch",
        "Girls Hair Brow"
      ],
      "i_top": 0,
      "i_newest": 0,
      "i_sgg": 0,
      "h_img": 1358,
      "w_img": 956,
      "date_img_modified": 1645540989252,
      "file_size": "157.79 Kb"
    },
    {
      "id_img": "Original_697416_crop2608_937639845",
      "lik": "UTb0sGqADnbLiHq9qhRMRkSRiLND0Tk7ctN8tpraiif/EHtzHicM0sk6i4MCKZSd2AZR48Hgrrxtk4msPv8mtpVy4706IhQgSYlgwrgVRHU=",
      "thub": "UTb0sGqADnbLiHq9qhRMRkSRiLND0Tk7ctN8tpraiif/EHtzHicM0sk6i4MCKZSdQNTbeK7mC/sYaZZMjfGsJpVy4706IhQgSYlgwrgVRHU=",
      "albl": [
        "Girls",
        "Original"
      ],
      "norl": [],
      "spel": [
        "Girls Uniform",
        "Girls Eyes Pink",
        "Girls Long Hair",
        "Girls Smile",
        "Girls Tie Bows",
        "Girls Hair Brow"
      ],
      "i_top": 0,
      "i_newest": 0,
      "i_sgg": 0,
      "h_img": 1080,
      "w_img": 760,
      "date_img_modified": 1645540988898,
      "file_size": "108.24 Kb"
    },
    {
      "id_img": "Original_697381_crop2608_1357733752",
      "lik": "UTb0sGqADnbLiHq9qhRMRkSRiLND0Tk7ctN8tpraiifuwBXIz/7XAojiVjFujgpX5J5DiPb9Md57RfQrSyLXv5Vy4706IhQgSYlgwrgVRHU=",
      "thub": "UTb0sGqADnbLiHq9qhRMRkSRiLND0Tk7ctN8tpraiifuwBXIz/7XAojiVjFujgpXQVDeQ6O89WmTouMRAVMLYpVy4706IhQgSYlgwrgVRHU=",
      "albl": [
        "Girls",
        "Original"
      ],
      "norl": [],
      "spel": [
        "Girls Hair Yellow",
        "Girls Short Hair",
        "Girls Long Hair",
        "Girls Kimono Yukata Cheongsam",
        "Girls Tie Bows",
        "Girls Eyes Blue"
      ],
      "i_top": 0,
      "i_newest": 0,
      "i_sgg": 0,
      "h_img": 1080,
      "w_img": 760,
      "date_img_modified": 1645540988611,
      "file_size": "123.30 Kb"
    },
    {
      "id_img": "Original_696862_crop2608_723084881",
      "lik": "UTb0sGqADnbLiHq9qhRMRkSRiLND0Tk7ctN8tpraiiepMHFb5dndnWKwlsOLQNfAJAQhY2/Ua7X+/nVV0dNuqZVy4706IhQgSYlgwrgVRHU=",
      "thub": "UTb0sGqADnbLiHq9qhRMRkSRiLND0Tk7ctN8tpraiiepMHFb5dndnWKwlsOLQNfAa0yZterkNANX/bE/e4xQaZVy4706IhQgSYlgwrgVRHU=",
      "albl": [
        "Girls",
        "Original"
      ],
      "norl": [
        "Butterfly",
        "Headdress",
        "Lamp",
        "Yukata",
        "Cherry Blossom",
        "Pointed Ears",
        "Instrument",
        "Flower",
        "Japanese Clothes"
      ],
      "spel": [
        "Girls Hair Silver",
        "Girls Hair White",
        "Girls Eyes Red",
        "Girls Long Hair",
        "Girls Music",
        "Girls Ears Neko",
        "Girls Kimono Yukata Cheongsam",
        "Girls Tie Bows"
      ],
      "i_top": 0,
      "i_newest": 0,
      "i_sgg": 0,
      "h_img": 1559,
      "w_img": 1097,
      "date_img_modified": 1645540984413,
      "file_size": "366.62 Kb"
    },
    {
      "id_img": "Original_696862_crop2608_-1234927135",
      "lik": "UTb0sGqADnbLiHq9qhRMRkSRiLND0Tk7ctN8tpraiid+8sGrxdDE7qKWuKyqCKKaJYhSZ8raN/FrPHgZUTkEHpVy4706IhQgSYlgwrgVRHU=",
      "thub": "UTb0sGqADnbLiHq9qhRMRkSRiLND0Tk7ctN8tpraiid+8sGrxdDE7qKWuKyqCKKa5ThiJnPvo24y2kvBbouQZJVy4706IhQgSYlgwrgVRHU=",
      "albl": [
        "Girls",
        "Original"
      ],
      "norl": [
        "Butterfly",
        "Headdress",
        "Lamp",
        "Yukata",
        "Cherry Blossom",
        "Pointed Ears",
        "Instrument",
        "Flower",
        "Japanese Clothes"
      ],
      "spel": [
        "Girls Hair Silver",
        "Girls Hair White",
        "Girls Eyes Red",
        "Girls Long Hair",
        "Girls Ears Neko",
        "Girls Kimono Yukata Cheongsam",
        "Girls Tie Bows"
      ],
      "i_top": 0,
      "i_newest": 0,
      "i_sgg": 0,
      "h_img": 1559,
      "w_img": 1097,
      "date_img_modified": 1645540984326,
      "file_size": "356.39 Kb"
    },
    {
      "id_img": "Original_696740_crop2608_-287304800",
      "lik": "UTb0sGqADnbLiHq9qhRMRkSRiLND0Tk7ctN8tpraiifnEYo5WIlpDT0pAOPkEgLnf19yi0gJfd8Gawcvz1jqD5Vy4706IhQgSYlgwrgVRHU=",
      "thub": "UTb0sGqADnbLiHq9qhRMRkSRiLND0Tk7ctN8tpraiifnEYo5WIlpDT0pAOPkEgLnxaWSEPRCmy3N7+n2SNWDCJVy4706IhQgSYlgwrgVRHU=",
      "albl": [
        "Girls",
        "Original"
      ],
      "norl": [],
      "spel": [
        "Girls Hair Black",
        "Girls Dark",
        "Dark Black",
        "Girls Eyes Red",
        "Girls Long Hair",
        "Girls Music",
        "Girls Smile",
        "Girls Hair Brow"
      ],
      "i_top": 0,
      "i_newest": 0,
      "i_sgg": 0,
      "h_img": 1600,
      "w_img": 1126,
      "date_img_modified": 1645540982348,
      "file_size": "81.53 Kb"
    },
    {
      "id_img": "Original_696619_crop2608_574052427",
      "lik": "UTb0sGqADnbLiHq9qhRMRkSRiLND0Tk7ctN8tpraiifFTiUjCIrY6tLvnh2lqwpZ+oUz6oBj/5eRA+p8IOh1BZVy4706IhQgSYlgwrgVRHU=",
      "thub": "UTb0sGqADnbLiHq9qhRMRkSRiLND0Tk7ctN8tpraiifFTiUjCIrY6tLvnh2lqwpZlRi5sNbQu0qvThO8nvMd4pVy4706IhQgSYlgwrgVRHU=",
      "albl": [
        "Girls",
        "Original"
      ],
      "norl": [],
      "spel": [
        "Girls Student",
        "Girls Short Hair",
        "Girls Hair Brow"
      ],
      "i_top": 0,
      "i_newest": 0,
      "i_sgg": 0,
      "h_img": 1080,
      "w_img": 760,
      "date_img_modified": 1645540980025,
      "file_size": "134.84 Kb"
    },
    {
      "id_img": "Original_696482_crop2608_920700315",
      "lik": "UTb0sGqADnbLiHq9qhRMRkSRiLND0Tk7ctN8tpraiidNQ2p9Lwp7k/d/ki9BNa/o4DCtEM3llcfuL+Enf0AdRJVy4706IhQgSYlgwrgVRHU=",
      "thub": "UTb0sGqADnbLiHq9qhRMRkSRiLND0Tk7ctN8tpraiidNQ2p9Lwp7k/d/ki9BNa/oEpImuOxf3rUs+KUJz/GT5JVy4706IhQgSYlgwrgVRHU=",
      "albl": [
        "Girls",
        "Original"
      ],
      "norl": [
        "Katana"
      ],
      "spel": [
        "Girls Hair Black",
        "Girls Horns",
        "Girls Eyes Red",
        "Girls Long Hair",
        "Girls Kimono Yukata Cheongsam",
        "Girls Tie Bows"
      ],
      "i_top": 0,
      "i_newest": 0,
      "i_sgg": 0,
      "h_img": 1617,
      "w_img": 1138,
      "date_img_modified": 1645540978531,
      "file_size": "156.07 Kb"
    },
    {
      "id_img": "Original_696455_crop2608_-1614976319",
      "lik": "UTb0sGqADnbLiHq9qhRMRkSRiLND0Tk7ctN8tpraiicIvMW8hdNZBSTq/QKlq0bCrCw8M5IUeJw+Lx6gve0Y/pVy4706IhQgSYlgwrgVRHU=",
      "thub": "UTb0sGqADnbLiHq9qhRMRkSRiLND0Tk7ctN8tpraiicIvMW8hdNZBSTq/QKlq0bCJMo7QSHrGxuHx2GBXF5QgJVy4706IhQgSYlgwrgVRHU=",
      "albl": [
        "Girls",
        "Original"
      ],
      "norl": [],
      "spel": [
        "Girls Hair Black",
        "Girls Eyes White",
        "Girls Eyes Yellow",
        "Girls Long Hair",
        "Girls Tie Bows"
      ],
      "i_top": 0,
      "i_newest": 0,
      "i_sgg": 0,
      "h_img": 1407,
      "w_img": 990,
      "date_img_modified": 1645540978083,
      "file_size": "202.76 Kb"
    },
    {
      "id_img": "Original_696324_crop2608_1350732002",
      "lik": "UTb0sGqADnbLiHq9qhRMRkSRiLND0Tk7ctN8tpraiif9uUnZ8Mn7ya+PIMI5zcGVFnRZ5lwLhnyiQp7PfOmXBpVy4706IhQgSYlgwrgVRHU=",
      "thub": "UTb0sGqADnbLiHq9qhRMRkSRiLND0Tk7ctN8tpraiif9uUnZ8Mn7ya+PIMI5zcGVrj6Ps3e7DAbKRcB7hflUl5Vy4706IhQgSYlgwrgVRHU=",
      "albl": [
        "Girls",
        "Original"
      ],
      "norl": [],
      "spel": [
        "Girls Uniform",
        "Girls Long Hair",
        "Girls Hats",
        "Girls Hair Blue",
        "Girls Smile",
        "Girls Tie Bows",
        "Girls Eyes Blue"
      ],
      "i_top": 0,
      "i_newest": 0,
      "i_sgg": 0,
      "h_img": 1355,
      "w_img": 953,
      "date_img_modified": 1645540977647,
      "file_size": "184.97 Kb"
    },
    {
      "id_img": "Original_696150_crop2608_-327762567",
      "lik": "UTb0sGqADnbLiHq9qhRMRkSRiLND0Tk7ctN8tpraiifj/p8JxjSlWqhrbwAbp8ffKGEVBD5dLOhxIx0ynAi1K5Vy4706IhQgSYlgwrgVRHU=",
      "thub": "UTb0sGqADnbLiHq9qhRMRkSRiLND0Tk7ctN8tpraiifj/p8JxjSlWqhrbwAbp8ff7RYgg45iUj8iT7DBLHJCWJVy4706IhQgSYlgwrgVRHU=",
      "albl": [
        "Girls",
        "Original"
      ],
      "norl": [],
      "spel": [
        "Girls Hair Black",
        "Girls Short Hair",
        "Girls Eyes Brown",
        "Girls Smile",
        "Girls Eyes Black",
        "Girls Tie Bows",
        "Girls Hair Brow"
      ],
      "i_top": 0,
      "i_newest": 0,
      "i_sgg": 0,
      "h_img": 1560,
      "w_img": 1098,
      "date_img_modified": 1645540976463,
      "file_size": "232.71 Kb"
    },
    {
      "id_img": "Original_696150_crop2608_-904679028",
      "lik": "UTb0sGqADnbLiHq9qhRMRkSRiLND0Tk7ctN8tpraiicnf4XGLQVsQTJ+eB0YfVeD9Ypcm7Rx93gXsdGPRaKD85Vy4706IhQgSYlgwrgVRHU=",
      "thub": "UTb0sGqADnbLiHq9qhRMRkSRiLND0Tk7ctN8tpraiicnf4XGLQVsQTJ+eB0YfVeDdbRbY7dbca7ggzIBQRoGbJVy4706IhQgSYlgwrgVRHU=",
      "albl": [
        "Girls",
        "Original"
      ],
      "norl": [],
      "spel": [
        "Girls Hair Black",
        "Girls Short Hair",
        "Girls Eyes Brown",
        "Girls Smile",
        "Girls Tie Bows"
      ],
      "i_top": 0,
      "i_newest": 0,
      "i_sgg": 0,
      "h_img": 1560,
      "w_img": 1098,
      "date_img_modified": 1645540976382,
      "file_size": "222.92 Kb"
    },
    {
      "id_img": "Original_695794_crop2608_-107663392",
      "lik": "UTb0sGqADnbLiHq9qhRMRkSRiLND0Tk7ctN8tpraiicNJK8Zg5LxQbOa00cMc//W6qh2Yf+rVmK+V5S7cbUJdJVy4706IhQgSYlgwrgVRHU=",
      "thub": "UTb0sGqADnbLiHq9qhRMRkSRiLND0Tk7ctN8tpraiicNJK8Zg5LxQbOa00cMc//WM0TpKtNou2jojx8Y+XZ265Vy4706IhQgSYlgwrgVRHU=",
      "albl": [
        "Girls",
        "Original"
      ],
      "norl": [
        "Sunglasses"
      ],
      "spel": [
        "Girls Glasses",
        "Girls Long Hair",
        "Girls Eyes Violet",
        "Girls Hair Blue",
        "Girls Tie Bows"
      ],
      "i_top": 0,
      "i_newest": 0,
      "i_sgg": 0,
      "h_img": 1260,
      "w_img": 887,
      "date_img_modified": 1645540975541,
      "file_size": "168.46 Kb"
    },
    {
      "id_img": "Original_695685_crop2608_557112897",
      "lik": "UTb0sGqADnbLiHq9qhRMRkSRiLND0Tk7ctN8tpraiid97J+QWZnHeZNrq0eQ4PHpx5MNgr0FX1ygGZABFmPzYJVy4706IhQgSYlgwrgVRHU=",
      "thub": "UTb0sGqADnbLiHq9qhRMRkSRiLND0Tk7ctN8tpraiid97J+QWZnHeZNrq0eQ4PHpIoZG6XKQZPcrImv3Uq6sipVy4706IhQgSYlgwrgVRHU=",
      "albl": [
        "Girls",
        "Original"
      ],
      "norl": [
        "Armor",
        "Blonde",
        "Gun",
        "Skirt"
      ],
      "spel": [
        "Girls Hair Silver",
        "Girls Uniform",
        "Girls Short Hair",
        "Girls Eyes Brown",
        "Girls Hair Grey",
        "Girls Tie Bows"
      ],
      "i_top": 0,
      "i_newest": 0,
      "i_sgg": 0,
      "h_img": 2480,
      "w_img": 1745,
      "date_img_modified": 1645540974850,
      "file_size": "369.27 Kb"
    },
    {
      "id_img": "Original_695330_crop2608_-1589092108",
      "lik": "UTb0sGqADnbLiHq9qhRMRkSRiLND0Tk7ctN8tpraiiejdY2dGLaOSA7slEmCCuVPdvbvuzkDMcuR9gRu9r8AsJVy4706IhQgSYlgwrgVRHU=",
      "thub": "UTb0sGqADnbLiHq9qhRMRkSRiLND0Tk7ctN8tpraiiejdY2dGLaOSA7slEmCCuVPGwRq2Of6zezUmyuUnkeQWJVy4706IhQgSYlgwrgVRHU=",
      "albl": [
        "Girls",
        "Original"
      ],
      "norl": [
        "Food",
        "Ponytail",
        "Lamp",
        "Glove",
        "Tail",
        "Scarf",
        "Book"
      ],
      "spel": [
        "Girls Hair Black",
        "Girls Hair Orange",
        "Girls Eyes Orange",
        "Girls Uniform",
        "Girls Long Hair",
        "Girls Hair Blue",
        "Girls Tie Bows"
      ],
      "i_top": 0,
      "i_newest": 0,
      "i_sgg": 0,
      "h_img": 1200,
      "w_img": 844,
      "date_img_modified": 1645540973219,
      "file_size": "109.25 Kb"
    },
    {
      "id_img": "Original_695314_crop2608_1963504366",
      "lik": "UTb0sGqADnbLiHq9qhRMRkSRiLND0Tk7ctN8tpraiidVFGd54+OUISIwckwJDodd55lYefqajcPt4/lJxM4TDpVy4706IhQgSYlgwrgVRHU=",
      "thub": "UTb0sGqADnbLiHq9qhRMRkSRiLND0Tk7ctN8tpraiidVFGd54+OUISIwckwJDoddnfJFyWOmcB5t6cSD/nIn7pVy4706IhQgSYlgwrgVRHU=",
      "albl": [
        "Girls",
        "Original"
      ],
      "norl": [
        "Blonde",
        "Chair",
        "Cat",
        "Tea",
        "Clock",
        "Cup",
        "Couch",
        "Book",
        "Blush",
        "Animal",
        "Table"
      ],
      "spel": [
        "Girls Hair Silver",
        "Girls Uniform",
        "Girls Hair Yellow",
        "Girls Short Hair",
        "Girls Eyes Brown",
        "Girls Long Hair",
        "Girls Hats",
        "Girls Maid",
        "Girls Smile",
        "Girls Tie Bows",
        "Girls Eyes Blue",
        "Girls Hair Brow"
      ],
      "i_top": 0,
      "i_newest": 0,
      "i_sgg": 0,
      "h_img": 1422,
      "w_img": 1001,
      "date_img_modified": 1645540972893,
      "file_size": "225.11 Kb"
    },
    {
      "id_img": "Original_695294_crop2608_1649551127",
      "lik": "UTb0sGqADnbLiHq9qhRMRkSRiLND0Tk7ctN8tpraiicspzcQuoYyj0xbnajpamhacHeAtl/HopWObVSfytf2jZVy4706IhQgSYlgwrgVRHU=",
      "thub": "UTb0sGqADnbLiHq9qhRMRkSRiLND0Tk7ctN8tpraiicspzcQuoYyj0xbnajpamhabApjZjmJbqN0SebkosDXLZVy4706IhQgSYlgwrgVRHU=",
      "albl": [
        "Girls",
        "Original"
      ],
      "norl": [
        "Thigh Highs",
        "School Uniform",
        "Blush"
      ],
      "spel": [
        "Girls Hair Black",
        "Girls Student",
        "Girls Eyes Yellow",
        "Girls Long Hair",
        "Girls Cute Cool",
        "Girls Smile",
        "Girls Tie Bows",
        "Girls Eyes Blue"
      ],
      "i_top": 0,
      "i_newest": 0,
      "i_sgg": 0,
      "h_img": 1200,
      "w_img": 844,
      "date_img_modified": 1645540972430,
      "file_size": "126.92 Kb"
    },
    {
      "id_img": "Original_695294_crop2608_1715722715",
      "lik": "UTb0sGqADnbLiHq9qhRMRkSRiLND0Tk7ctN8tpraiidH/TDbPhYsGNrRFBRl6b2znZRUPGKRwfDPF7XYY5/2cpVy4706IhQgSYlgwrgVRHU=",
      "thub": "UTb0sGqADnbLiHq9qhRMRkSRiLND0Tk7ctN8tpraiidH/TDbPhYsGNrRFBRl6b2z0W6GN0HMtRUnNw2E4HsiOZVy4706IhQgSYlgwrgVRHU=",
      "albl": [
        "Girls",
        "Original"
      ],
      "norl": [
        "Thigh Highs",
        "School Uniform",
        "Blush"
      ],
      "spel": [
        "Girls Hair Black",
        "Girls Student",
        "Girls Eyes Yellow",
        "Girls Long Hair",
        "Girls Cute Cool",
        "Girls Hats",
        "Girls Eyes Grey",
        "Girls Smile",
        "Girls Eyes Black",
        "Girls Tie Bows"
      ],
      "i_top": 0,
      "i_newest": 0,
      "i_sgg": 0,
      "h_img": 1200,
      "w_img": 844,
      "date_img_modified": 1645540972366,
      "file_size": "126.37 Kb"
    },
    {
      "id_img": "Original_695294_crop2608_-2082439570",
      "lik": "UTb0sGqADnbLiHq9qhRMRkSRiLND0Tk7ctN8tpraiidlgjJyN+QyhvPvMMOwNCqSKNPbUjs+aOzTkFuTNa3e+ZVy4706IhQgSYlgwrgVRHU=",
      "thub": "UTb0sGqADnbLiHq9qhRMRkSRiLND0Tk7ctN8tpraiidlgjJyN+QyhvPvMMOwNCqStRPuAhExJhYgbJnA5oZi+pVy4706IhQgSYlgwrgVRHU=",
      "albl": [
        "Girls",
        "Original"
      ],
      "norl": [
        "Thigh Highs",
        "School Uniform",
        "Blush"
      ],
      "spel": [
        "Girls Hair Black",
        "Girls Student",
        "Girls Long Hair",
        "Girls Cute Cool",
        "Girls Hats",
        "Girls Eyes Grey",
        "Girls Eyes Black",
        "Girls Tie Bows"
      ],
      "i_top": 0,
      "i_newest": 0,
      "i_sgg": 0,
      "h_img": 1200,
      "w_img": 844,
      "date_img_modified": 1645540972311,
      "file_size": "111.26 Kb"
    },
    {
      "id_img": "Original_695245_crop2608_1480978113",
      "lik": "UTb0sGqADnbLiHq9qhRMRkSRiLND0Tk7ctN8tpraiiepgFkamfRGn0oWIpR0TOiDu5umFxRFG1/6Hu08cdL3DJVy4706IhQgSYlgwrgVRHU=",
      "thub": "UTb0sGqADnbLiHq9qhRMRkSRiLND0Tk7ctN8tpraiiepgFkamfRGn0oWIpR0TOiDcWU8kdltuGcfekoFRp4cO5Vy4706IhQgSYlgwrgVRHU=",
      "albl": [
        "Girls",
        "Original"
      ],
      "norl": [
        "Sword",
        "Armor"
      ],
      "spel": [
        "Girls Uniform",
        "Girls Eyes Red",
        "Girls Long Hair",
        "Girls Hair Brow"
      ],
      "i_top": 0,
      "i_newest": 0,
      "i_sgg": 0,
      "h_img": 1519,
      "w_img": 1069,
      "date_img_modified": 1645540972031,
      "file_size": "163.82 Kb"
    },
    {
      "id_img": "Original_695200_crop2608_-653767213",
      "lik": "UTb0sGqADnbLiHq9qhRMRkSRiLND0Tk7ctN8tpraiie+0z10Yq3qwGjdkWFEA6iKvjiTTYBKl1nELHFKjAr9BZVy4706IhQgSYlgwrgVRHU=",
      "thub": "UTb0sGqADnbLiHq9qhRMRkSRiLND0Tk7ctN8tpraiie+0z10Yq3qwGjdkWFEA6iKmpjLnd0DRKejbfZk/4s9i5Vy4706IhQgSYlgwrgVRHU=",
      "albl": [
        "Girls",
        "Original"
      ],
      "norl": [
        "Armor",
        "Ponytail",
        "Warrior"
      ],
      "spel": [
        "Girls Hair Silver",
        "Girls Hair White",
        "Girls Uniform",
        "Girls Eyes Red",
        "Girls Long Hair",
        "Girls Tie Bows"
      ],
      "i_top": 0,
      "i_newest": 0,
      "i_sgg": 0,
      "h_img": 1137,
      "w_img": 800,
      "date_img_modified": 1645540971607,
      "file_size": "73.21 Kb"
    },
    {
      "id_img": "Original_695199_crop2608_-689762529",
      "lik": "UTb0sGqADnbLiHq9qhRMRkSRiLND0Tk7ctN8tpraiicN+piMDYCO3N69PNGfd0E2Qn8jWdlBGvXiRmVQhBIbFJVy4706IhQgSYlgwrgVRHU=",
      "thub": "UTb0sGqADnbLiHq9qhRMRkSRiLND0Tk7ctN8tpraiicN+piMDYCO3N69PNGfd0E2iMbTNZEYW+VQiFHASlWc2pVy4706IhQgSYlgwrgVRHU=",
      "albl": [
        "Girls",
        "Original"
      ],
      "norl": [
        "Glove",
        "Tail",
        "Winter",
        "Ball",
        "Blush"
      ],
      "spel": [
        "Girls Uniform",
        "Girls Short Hair",
        "Girls Eyes Yellow",
        "Girls Cute Cool",
        "Girls Hair Blue",
        "Girls Ears Neko",
        "Girls Smile",
        "Girls Tie Bows"
      ],
      "i_top": 0,
      "i_newest": 0,
      "i_sgg": 0,
      "h_img": 1500,
      "w_img": 1056,
      "date_img_modified": 1645540971233,
      "file_size": "131.53 Kb"
    },
    {
      "id_img": "Original_695198_crop2608_2097652958",
      "lik": "UTb0sGqADnbLiHq9qhRMRkSRiLND0Tk7ctN8tpraiid0nT1JAIpRatz/ZntpWe5uxTZOlpj6MqfDu53OH/adh5Vy4706IhQgSYlgwrgVRHU=",
      "thub": "UTb0sGqADnbLiHq9qhRMRkSRiLND0Tk7ctN8tpraiid0nT1JAIpRatz/ZntpWe5utBUQdgVtUtgY240R/V/aKJVy4706IhQgSYlgwrgVRHU=",
      "albl": [
        "Girls",
        "Original"
      ],
      "norl": [
        "Scarf"
      ],
      "spel": [
        "Girls Hair Silver",
        "Girls Hair White",
        "Girls Uniform",
        "Girls Short Hair",
        "Girls Eyes Red",
        "Girls Smile",
        "Girls Eyes Black",
        "Girls Tie Bows"
      ],
      "i_top": 0,
      "i_newest": 0,
      "i_sgg": 0,
      "h_img": 1000,
      "w_img": 704,
      "date_img_modified": 1645540970857,
      "file_size": "52.96 Kb"
    },
    {
      "id_img": "Original_694860_crop2608_-972417263",
      "lik": "UTb0sGqADnbLiHq9qhRMRkSRiLND0Tk7ctN8tpraiieP//hqzxbUMUD0CBimX5eN7lnm7M7OuOyJKIoq/PXQsJVy4706IhQgSYlgwrgVRHU=",
      "thub": "UTb0sGqADnbLiHq9qhRMRkSRiLND0Tk7ctN8tpraiieP//hqzxbUMUD0CBimX5eNUgbAIfqyIrAE44q1dX21xpVy4706IhQgSYlgwrgVRHU=",
      "albl": [
        "Girls",
        "Original"
      ],
      "norl": [],
      "spel": [
        "Girls Hair Black",
        "Girls Student",
        "Girls Eyes Brown",
        "Girls Long Hair",
        "Girls Smile",
        "Girls Tie Bows",
        "Girls Hair Brow"
      ],
      "i_top": 0,
      "i_newest": 0,
      "i_sgg": 0,
      "h_img": 1200,
      "w_img": 844,
      "date_img_modified": 1645540969961,
      "file_size": "118.36 Kb"
    },
    {
      "id_img": "Original_694812_crop2608_-983078840",
      "lik": "UTb0sGqADnbLiHq9qhRMRkSRiLND0Tk7ctN8tpraiifBY3uYbnAUOZ0p536BzmDGcPryfNycwqMf2CGFPnPzrJVy4706IhQgSYlgwrgVRHU=",
      "thub": "UTb0sGqADnbLiHq9qhRMRkSRiLND0Tk7ctN8tpraiifBY3uYbnAUOZ0p536BzmDGZUrPthbwyRW+vdlM7mRRK5Vy4706IhQgSYlgwrgVRHU=",
      "albl": [
        "Girls",
        "Original"
      ],
      "norl": [],
      "spel": [
        "Girls Student",
        "Girls Eyes Brown",
        "Girls Long Hair",
        "Girls Water Rain",
        "Girls Smile",
        "Girls Tie Bows",
        "Girls Hair Brow"
      ],
      "i_top": 0,
      "i_newest": 0,
      "i_sgg": 0,
      "h_img": 1200,
      "w_img": 844,
      "date_img_modified": 1645540968350,
      "file_size": "196.30 Kb"
    },
    {
      "id_img": "Original_694749_crop2608_-1905062997",
      "lik": "UTb0sGqADnbLiHq9qhRMRkSRiLND0Tk7ctN8tpraiieGkaEj4LorqT7KaPjxwWfq718HS5fV3DZE2Cx8mk1pTJVy4706IhQgSYlgwrgVRHU=",
      "thub": "UTb0sGqADnbLiHq9qhRMRkSRiLND0Tk7ctN8tpraiieGkaEj4LorqT7KaPjxwWfqESLm7jTT8mt0Fw/mxMuRopVy4706IhQgSYlgwrgVRHU=",
      "albl": [
        "Girls",
        "Original"
      ],
      "norl": [
        "Wings"
      ],
      "spel": [
        "Girls Hair Silver",
        "Girls Dark",
        "Dark Black",
        "Girls Hair Grey",
        "Girls Long Hair",
        "Girls Eyes Blue"
      ],
      "i_top": 0,
      "i_newest": 0,
      "i_sgg": 0,
      "h_img": 3665,
      "w_img": 2580,
      "date_img_modified": 1645540967730,
      "file_size": "597.68 Kb"
    },
    {
      "id_img": "Original_694550_crop2608_-1510313665",
      "lik": "UTb0sGqADnbLiHq9qhRMRkSRiLND0Tk7ctN8tpraiieIAODvxWq6TjZ1wtmrynm8WQZdBU90RW0SnNn8H/ZtV5Vy4706IhQgSYlgwrgVRHU=",
      "thub": "UTb0sGqADnbLiHq9qhRMRkSRiLND0Tk7ctN8tpraiieIAODvxWq6TjZ1wtmrynm8Or6pGK9QBTctEyIC7dqLvZVy4706IhQgSYlgwrgVRHU=",
      "albl": [
        "Girls",
        "Original"
      ],
      "norl": [],
      "spel": [
        "Girls Hair Black",
        "Girls Dark",
        "Dark Black",
        "Sad",
        "Girls Eyes Brown",
        "Girls Sad",
        "Girls Long Hair",
        "Girls Tears",
        "Girls Tie Bows"
      ],
      "i_top": 0,
      "i_newest": 0,
      "i_sgg": 0,
      "h_img": 1023,
      "w_img": 720,
      "date_img_modified": 1645540965992,
      "file_size": "142.98 Kb"
    },
    {
      "id_img": "Original_694544_crop2608_735460452",
      "lik": "UTb0sGqADnbLiHq9qhRMRkSRiLND0Tk7ctN8tpraiicd2oL+2VMMWqdiXbv4aEN22lMZufSbHGfebHdIHsYmBJVy4706IhQgSYlgwrgVRHU=",
      "thub": "UTb0sGqADnbLiHq9qhRMRkSRiLND0Tk7ctN8tpraiicd2oL+2VMMWqdiXbv4aEN2JzyiTl1trNon6SVkkmE2bZVy4706IhQgSYlgwrgVRHU=",
      "albl": [
        "Girls",
        "Original"
      ],
      "norl": [],
      "spel": [
        "Girls Hair Black",
        "Girls Student",
        "Girls Short Hair",
        "Girls Eyes Brown",
        "Girls Long Hair",
        "Girls Water Rain",
        "Girls Smile",
        "Girls Tie Bows",
        "Girls Hair Brow"
      ],
      "i_top": 0,
      "i_newest": 0,
      "i_sgg": 0,
      "h_img": 1080,
      "w_img": 760,
      "date_img_modified": 1645540965159,
      "file_size": "106.29 Kb"
    },
    {
      "id_img": "Original_694288_crop2608_663601889",
      "lik": "UTb0sGqADnbLiHq9qhRMRkSRiLND0Tk7ctN8tpraiifbUP62kHQfU/6VvcBB4KV31W27vQuX5SqwZAiJyxddGZVy4706IhQgSYlgwrgVRHU=",
      "thub": "UTb0sGqADnbLiHq9qhRMRkSRiLND0Tk7ctN8tpraiifbUP62kHQfU/6VvcBB4KV3RVknkNWigjEGrqGZ7Wxqc5Vy4706IhQgSYlgwrgVRHU=",
      "albl": [
        "Girls",
        "Original"
      ],
      "norl": [
        "Headdress",
        "Lips",
        "Blush"
      ],
      "spel": [
        "Girls Hair Black",
        "Sad",
        "Girls Eyes Brown",
        "Girls Sad",
        "Girls Long Hair",
        "Girls Tie Bows",
        "Girls Hair Brow"
      ],
      "i_top": 0,
      "i_newest": 0,
      "i_sgg": 0,
      "h_img": 1982,
      "w_img": 1395,
      "date_img_modified": 1645540964816,
      "file_size": "184.00 Kb"
    },
    {
      "id_img": "Original_694195_crop2608_-1427930116",
      "lik": "UTb0sGqADnbLiHq9qhRMRkSRiLND0Tk7ctN8tpraiieUqJTjWbo6A1eAuSjzDK8Vx7kF02NjCw8xX3vLvXYRBpVy4706IhQgSYlgwrgVRHU=",
      "thub": "UTb0sGqADnbLiHq9qhRMRkSRiLND0Tk7ctN8tpraiieUqJTjWbo6A1eAuSjzDK8V0H2CMZBuUh9MapA5AjP5V5Vy4706IhQgSYlgwrgVRHU=",
      "albl": [
        "Girls",
        "Original"
      ],
      "norl": [],
      "spel": [
        "Girls Hair Silver",
        "Girls Hair White",
        "Girls Short Hair",
        "Girls Eyes Red",
        "Girls Cute Cool",
        "Girls Smile",
        "Girls Tie Bows"
      ],
      "i_top": 0,
      "i_newest": 0,
      "i_sgg": 0,
      "h_img": 1080,
      "w_img": 760,
      "date_img_modified": 1645540964344,
      "file_size": "104.62 Kb"
    },
    {
      "id_img": "Original_693587_crop2608_-81915772",
      "lik": "UTb0sGqADnbLiHq9qhRMRkSRiLND0Tk7ctN8tpraiidKgjjA/xVjunClkSsKYJcUI/BqDMx0V8Tb6CG5Am0zh5Vy4706IhQgSYlgwrgVRHU=",
      "thub": "UTb0sGqADnbLiHq9qhRMRkSRiLND0Tk7ctN8tpraiidKgjjA/xVjunClkSsKYJcUaq0njXgRbfBJOHHOl6OfApVy4706IhQgSYlgwrgVRHU=",
      "albl": [
        "Girls",
        "Original"
      ],
      "norl": [],
      "spel": [
        "Girls Uniform",
        "Girls Short Hair",
        "Girls Eyes Red",
        "Girls Glasses",
        "Girls Cute Cool",
        "Girls Hair Red",
        "Girls Smile",
        "Girls Scarf",
        "Girls Tie Bows"
      ],
      "i_top": 0,
      "i_newest": 0,
      "i_sgg": 0,
      "h_img": 1250,
      "w_img": 880,
      "date_img_modified": 1645540964042,
      "file_size": "140.65 Kb"
    },
    {
      "id_img": "Original_693524_crop2608_-1541366137",
      "lik": "UTb0sGqADnbLiHq9qhRMRkSRiLND0Tk7ctN8tpraiidhIucZ9HPUfiAjCnFWcUqth0jrKIKzb/CxmlYbPk0aaZVy4706IhQgSYlgwrgVRHU=",
      "thub": "UTb0sGqADnbLiHq9qhRMRkSRiLND0Tk7ctN8tpraiidhIucZ9HPUfiAjCnFWcUqtP/8Ve42F8PHSxWTdkGfkYZVy4706IhQgSYlgwrgVRHU=",
      "albl": [
        "Girls",
        "Original"
      ],
      "norl": [],
      "spel": [
        "Girls Hair Silver",
        "Girls Hair White",
        "Girls Hair Grey",
        "Girls Long Hair",
        "Girls Face Masks",
        "Girls Smile",
        "Girls Eyes Blue"
      ],
      "i_top": 0,
      "i_newest": 0,
      "i_sgg": 0,
      "h_img": 1080,
      "w_img": 760,
      "date_img_modified": 1645540962632,
      "file_size": "172.09 Kb"
    },
    {
      "id_img": "Original_693513_crop2608_1756583527",
      "lik": "UTb0sGqADnbLiHq9qhRMRkSRiLND0Tk7ctN8tpraiifuvOCQW9ynZoPI3zJyIBiWmQRjXeXrk/qKMEY4S2Q+xZVy4706IhQgSYlgwrgVRHU=",
      "thub": "UTb0sGqADnbLiHq9qhRMRkSRiLND0Tk7ctN8tpraiifuvOCQW9ynZoPI3zJyIBiWA2ftS68SN4XRw7k2DmAB/pVy4706IhQgSYlgwrgVRHU=",
      "albl": [
        "Girls",
        "Original"
      ],
      "norl": [],
      "spel": [
        "Girls Hair Orange",
        "Girls Student",
        "Girls Hair Yellow",
        "Girls Long Hair",
        "Girls Cute Cool",
        "Girls Maid",
        "Girls Smile",
        "Girls Tie Bows",
        "Girls Eyes Blue"
      ],
      "i_top": 0,
      "i_newest": 0,
      "i_sgg": 0,
      "h_img": 1254,
      "w_img": 882,
      "date_img_modified": 1645540962259,
      "file_size": "164.19 Kb"
    },
    {
      "id_img": "Original_693385_crop2608_-1508671488",
      "lik": "UTb0sGqADnbLiHq9qhRMRkSRiLND0Tk7ctN8tpraiifGyPZSS8RF8nO7737pXsll7X35MW0r/XGkmG5M/NvBSJVy4706IhQgSYlgwrgVRHU=",
      "thub": "UTb0sGqADnbLiHq9qhRMRkSRiLND0Tk7ctN8tpraiifGyPZSS8RF8nO7737pXsllCjX+oncKQeamKue/W+WJu5Vy4706IhQgSYlgwrgVRHU=",
      "albl": [
        "Girls",
        "Original"
      ],
      "norl": [],
      "spel": [
        "Girls Uniform",
        "Girls Short Hair",
        "Girls Hair Pink",
        "Girls Eyes Yellow"
      ],
      "i_top": 0,
      "i_newest": 0,
      "i_sgg": 0,
      "h_img": 2554,
      "w_img": 1798,
      "date_img_modified": 1645540960669,
      "file_size": "268.26 Kb"
    },
    {
      "id_img": "Original_693279_crop2608_1989969582",
      "lik": "UTb0sGqADnbLiHq9qhRMRkSRiLND0Tk7ctN8tpraiic1vlv9sSI0WRXcsgwjYi8o2/RpgLkgP6Jh0gHW9Ifq05Vy4706IhQgSYlgwrgVRHU=",
      "thub": "UTb0sGqADnbLiHq9qhRMRkSRiLND0Tk7ctN8tpraiic1vlv9sSI0WRXcsgwjYi8oxqFVFb1ZwQGuuJ3l8XtmMJVy4706IhQgSYlgwrgVRHU=",
      "albl": [
        "Girls",
        "Original"
      ],
      "norl": [
        "Wink",
        "Feather",
        "Blush"
      ],
      "spel": [
        "Girls Hair Black",
        "Girls Long Hair",
        "Girls Cute Cool",
        "Girls Smile",
        "Girls Tie Bows",
        "Girls Eyes Blue"
      ],
      "i_top": 0,
      "i_newest": 0,
      "i_sgg": 0,
      "h_img": 1532,
      "w_img": 1078,
      "date_img_modified": 1645540959697,
      "file_size": "113.56 Kb"
    },
    {
      "id_img": "Original_692887_crop2608_680118376",
      "lik": "UTb0sGqADnbLiHq9qhRMRkSRiLND0Tk7ctN8tpraiie5h+T2OlXRBFFQBtnhNTMrpaNb3lKBnv5TGh7n6s6CVJVy4706IhQgSYlgwrgVRHU=",
      "thub": "UTb0sGqADnbLiHq9qhRMRkSRiLND0Tk7ctN8tpraiie5h+T2OlXRBFFQBtnhNTMrgfQ3iF3+DgHxDKNyLcMouZVy4706IhQgSYlgwrgVRHU=",
      "albl": [
        "Girls",
        "Original"
      ],
      "norl": [
        "Skirt",
        "Mecha"
      ],
      "spel": [
        "Girls Uniform",
        "Girls Short Hair",
        "Girls Eyes Red",
        "Girls Hair Blue",
        "Girls Ears Neko",
        "Girls Tie Bows"
      ],
      "i_top": 0,
      "i_newest": 0,
      "i_sgg": 0,
      "h_img": 1440,
      "w_img": 1013,
      "date_img_modified": 1645540958447,
      "file_size": "127.69 Kb"
    },
    {
      "id_img": "Original_692771_crop2608_-618033406",
      "lik": "UTb0sGqADnbLiHq9qhRMRkSRiLND0Tk7ctN8tpraiiePFQrhZ5WJIto7sTKjFrtmCcL4z13DGBtwgfvkN7+/eJVy4706IhQgSYlgwrgVRHU=",
      "thub": "UTb0sGqADnbLiHq9qhRMRkSRiLND0Tk7ctN8tpraiiePFQrhZ5WJIto7sTKjFrtm6O7cyeZ2QQ3Oe3VXgiz7w5Vy4706IhQgSYlgwrgVRHU=",
      "albl": [
        "Girls",
        "Original"
      ],
      "norl": [],
      "spel": [
        "Girls Uniform",
        "Girls Dark",
        "Girls Hair Pink",
        "Dark Black",
        "Girls Eyes Red",
        "Girls Long Hair",
        "Girls Smile",
        "Girls Tie Bows"
      ],
      "i_top": 0,
      "i_newest": 0,
      "i_sgg": 0,
      "h_img": 1080,
      "w_img": 760,
      "date_img_modified": 1645540957674,
      "file_size": "107.00 Kb"
    },
    {
      "id_img": "Original_692768_crop2608_1855428842",
      "lik": "UTb0sGqADnbLiHq9qhRMRkSRiLND0Tk7ctN8tpraiif49QqZjHuUiOsoeDwww00oOh+mp47fu18pTuI7jdCbipVy4706IhQgSYlgwrgVRHU=",
      "thub": "UTb0sGqADnbLiHq9qhRMRkSRiLND0Tk7ctN8tpraiif49QqZjHuUiOsoeDwww00omvXS/XAtq5hYIvPP0dVGe5Vy4706IhQgSYlgwrgVRHU=",
      "albl": [
        "Girls",
        "Original"
      ],
      "norl": [],
      "spel": [
        "Girls Hair Black",
        "Girls Eyes Brown",
        "Girls Long Hair",
        "Girls Smile",
        "Girls Kimono Yukata Cheongsam",
        "Girls Tie Bows",
        "Girls Hair Brow"
      ],
      "i_top": 0,
      "i_newest": 0,
      "i_sgg": 0,
      "h_img": 1080,
      "w_img": 760,
      "date_img_modified": 1645540957341,
      "file_size": "128.78 Kb"
    },
    {
      "id_img": "Original_692764_crop2608_120188902",
      "lik": "UTb0sGqADnbLiHq9qhRMRkSRiLND0Tk7ctN8tpraiidRd8gZZbkyl0+d/6IAfAU6kDSKL1xEhroV4GIiR1J4zJVy4706IhQgSYlgwrgVRHU=",
      "thub": "UTb0sGqADnbLiHq9qhRMRkSRiLND0Tk7ctN8tpraiidRd8gZZbkyl0+d/6IAfAU6Sw9c9R07JFzu3yoA1O8z7pVy4706IhQgSYlgwrgVRHU=",
      "albl": [
        "Girls",
        "Original"
      ],
      "norl": [],
      "spel": [
        "Girls Student",
        "Sad",
        "Girls Sad",
        "Girls Long Hair",
        "Girls Eyes Black",
        "Girls Tie Bows",
        "Girls Hair Brow"
      ],
      "i_top": 0,
      "i_newest": 0,
      "i_sgg": 0,
      "h_img": 1158,
      "w_img": 815,
      "date_img_modified": 1645540956387,
      "file_size": "70.30 Kb"
    },
    {
      "id_img": "Original_692624_crop2608_809015913",
      "lik": "UTb0sGqADnbLiHq9qhRMRkSRiLND0Tk7ctN8tpraiie7bzhUm7TkmIxSbVTTKQetImFDyw5EtXkmmLd7E424yJVy4706IhQgSYlgwrgVRHU=",
      "thub": "UTb0sGqADnbLiHq9qhRMRkSRiLND0Tk7ctN8tpraiie7bzhUm7TkmIxSbVTTKQet+N9FQHPyIagaC6LUhTyvBJVy4706IhQgSYlgwrgVRHU=",
      "albl": [
        "Girls",
        "Original"
      ],
      "norl": [
        "Bag",
        "Train",
        "Blush"
      ],
      "spel": [
        "Girls Hair Black",
        "Girls Long Hair",
        "Girls Cute Cool",
        "Girls Smile",
        "Girls Tie Bows",
        "Girls Eyes Blue"
      ],
      "i_top": 0,
      "i_newest": 0,
      "i_sgg": 0,
      "h_img": 1280,
      "w_img": 901,
      "date_img_modified": 1645540956105,
      "file_size": "98.27 Kb"
    },
    {
      "id_img": "Original_692552_crop2608_-796032637",
      "lik": "UTb0sGqADnbLiHq9qhRMRkSRiLND0Tk7ctN8tpraiiejzYgRfuSIAJUG0Zc8TBvBKey7T2DCT21aCbDxs/S1VZVy4706IhQgSYlgwrgVRHU=",
      "thub": "UTb0sGqADnbLiHq9qhRMRkSRiLND0Tk7ctN8tpraiiejzYgRfuSIAJUG0Zc8TBvBtSQlv0Z0u0XalK6t1ep4V5Vy4706IhQgSYlgwrgVRHU=",
      "albl": [
        "Girls",
        "Original"
      ],
      "norl": [],
      "spel": [
        "Girls Hair Silver",
        "Girls Hair White",
        "Girls Long Hair",
        "Girls Smile",
        "Girls Tie Bows",
        "Girls Eyes Blue"
      ],
      "i_top": 0,
      "i_newest": 0,
      "i_sgg": 0,
      "h_img": 1227,
      "w_img": 863,
      "date_img_modified": 1645540955446,
      "file_size": "161.93 Kb"
    },
    {
      "id_img": "Original_692514_crop2608_1177474217",
      "lik": "UTb0sGqADnbLiHq9qhRMRkSRiLND0Tk7ctN8tpraiif3KUC4+TuQHzXt+FwuhBYO7p0EeyXazFAl43AM5T0DRpVy4706IhQgSYlgwrgVRHU=",
      "thub": "UTb0sGqADnbLiHq9qhRMRkSRiLND0Tk7ctN8tpraiif3KUC4+TuQHzXt+FwuhBYOmoVArf7VzfmEDVeMR4QZTZVy4706IhQgSYlgwrgVRHU=",
      "albl": [
        "Girls",
        "Original"
      ],
      "norl": [],
      "spel": [
        "Girls Hair Black",
        "Girls Short Hair"
      ],
      "i_top": 0,
      "i_newest": 0,
      "i_sgg": 0,
      "h_img": 1210,
      "w_img": 851,
      "date_img_modified": 1645540955181,
      "file_size": "89.23 Kb"
    },
    {
      "id_img": "Original_692510_crop2608_599964824",
      "lik": "UTb0sGqADnbLiHq9qhRMRkSRiLND0Tk7ctN8tpraiif+kohaVxtvaiy/64Wj8EAR11v0sKB54iMvpg0R1KHOM5Vy4706IhQgSYlgwrgVRHU=",
      "thub": "UTb0sGqADnbLiHq9qhRMRkSRiLND0Tk7ctN8tpraiif+kohaVxtvaiy/64Wj8EAR/gO4OSo6MmK2KDSLfp3D6ZVy4706IhQgSYlgwrgVRHU=",
      "albl": [
        "Girls",
        "Original"
      ],
      "norl": [
        "Leaf",
        "Blonde",
        "Rabbit",
        "Squirrel",
        "Tree",
        "Building",
        "Bird",
        "Apron",
        "Digital Art",
        "Blush",
        "Animal"
      ],
      "spel": [
        "Girls Hair Yellow",
        "Girls Dark",
        "Dark Black",
        "Girls Eyes Red",
        "Girls Long Hair"
      ],
      "i_top": 0,
      "i_newest": 0,
      "i_sgg": 0,
      "h_img": 1230,
      "w_img": 865,
      "date_img_modified": 1645540954656,
      "file_size": "222.83 Kb"
    },
    {
      "id_img": "Original_692205_crop2608_-2075602712",
      "lik": "UTb0sGqADnbLiHq9qhRMRkSRiLND0Tk7ctN8tpraiid/mXRX+Db1uol5eZXs/aFt7ZEoASXc3/iws9mvEBAEn5Vy4706IhQgSYlgwrgVRHU=",
      "thub": "UTb0sGqADnbLiHq9qhRMRkSRiLND0Tk7ctN8tpraiid/mXRX+Db1uol5eZXs/aFtHyE0r94mgGJECk/+YnexcJVy4706IhQgSYlgwrgVRHU=",
      "albl": [
        "Girls",
        "Original"
      ],
      "norl": [
        "Dove",
        "Bird"
      ],
      "spel": [
        "Girls Hair Black",
        "Girls Eyes Brown",
        "Girls Long Hair",
        "Girls Hats",
        "Girls Tie Bows"
      ],
      "i_top": 0,
      "i_newest": 0,
      "i_sgg": 0,
      "h_img": 1229,
      "w_img": 865,
      "date_img_modified": 1645540953494,
      "file_size": "246.03 Kb"
    },
    {
      "id_img": "Original_692201_crop2608_484124644",
      "lik": "UTb0sGqADnbLiHq9qhRMRkSRiLND0Tk7ctN8tpraiiemaOSbdl7g7k8vU4YWwC3CQR84xYvfXUfWdpb5/u6KDpVy4706IhQgSYlgwrgVRHU=",
      "thub": "UTb0sGqADnbLiHq9qhRMRkSRiLND0Tk7ctN8tpraiiemaOSbdl7g7k8vU4YWwC3CO37LRwkUehoJNwDYT3UxVJVy4706IhQgSYlgwrgVRHU=",
      "albl": [
        "Girls",
        "Original"
      ],
      "norl": [],
      "spel": [
        "Girls Hair Silver",
        "Girls Student",
        "Girls Hair White",
        "Girls Horns",
        "Girls Eyes Red",
        "Girls Long Hair",
        "Girls Tie Bows"
      ],
      "i_top": 0,
      "i_newest": 0,
      "i_sgg": 0,
      "h_img": 1173,
      "w_img": 825,
      "date_img_modified": 1645540953075,
      "file_size": "119.31 Kb"
    },
    {
      "id_img": "Original_692078_crop2608_461661378",
      "lik": "UTb0sGqADnbLiHq9qhRMRkSRiLND0Tk7ctN8tpraiie+JwaI24B+P7paTUVb9T8eU76WOyjKH6YgA+9p1Mx8LpVy4706IhQgSYlgwrgVRHU=",
      "thub": "UTb0sGqADnbLiHq9qhRMRkSRiLND0Tk7ctN8tpraiie+JwaI24B+P7paTUVb9T8eZFcOaVw0pR675oHsFzIBr5Vy4706IhQgSYlgwrgVRHU=",
      "albl": [
        "Girls",
        "Original"
      ],
      "norl": [],
      "spel": [
        "Girls Student",
        "Girls Dark",
        "Dark Black",
        "Sad",
        "Girls Sad",
        "Girls Long Hair",
        "Girls Water Rain",
        "Girls Cute Cool",
        "Girls Tears",
        "Girls Tie Bows",
        "Girls Hair Brow"
      ],
      "i_top": 0,
      "i_newest": 0,
      "i_sgg": 0,
      "h_img": 2160,
      "w_img": 1520,
      "date_img_modified": 1645540952075,
      "file_size": "210.12 Kb"
    },
    {
      "id_img": "Original_692077_crop2608_-1045890431",
      "lik": "UTb0sGqADnbLiHq9qhRMRkSRiLND0Tk7ctN8tpraiicLRGPUMwCMxKk9Sm8q4h3wd9MRt2cqxlycb8gQBk3YGJVy4706IhQgSYlgwrgVRHU=",
      "thub": "UTb0sGqADnbLiHq9qhRMRkSRiLND0Tk7ctN8tpraiicLRGPUMwCMxKk9Sm8q4h3wrU5BD/e6R8LpC67tPtW2KpVy4706IhQgSYlgwrgVRHU=",
      "albl": [
        "Girls",
        "Original"
      ],
      "norl": [
        "Feather"
      ],
      "spel": [
        "Girls Student",
        "Girls Eyes Brown",
        "Girls Long Hair",
        "Girls Tie Bows",
        "Girls Hair Brow"
      ],
      "i_top": 0,
      "i_newest": 0,
      "i_sgg": 0,
      "h_img": 1080,
      "w_img": 760,
      "date_img_modified": 1645540951514,
      "file_size": "78.18 Kb"
    },
    {
      "id_img": "Original_691507_crop2608_1701535054",
      "lik": "UTb0sGqADnbLiHq9qhRMRkSRiLND0Tk7ctN8tpraiiecT2DpXaI4bXBTTeLTNWOw+ZnP8nFMp2eCKA8vNxfFxZVy4706IhQgSYlgwrgVRHU=",
      "thub": "UTb0sGqADnbLiHq9qhRMRkSRiLND0Tk7ctN8tpraiiecT2DpXaI4bXBTTeLTNWOwxCYb5JefMawDoY2RZveB3pVy4706IhQgSYlgwrgVRHU=",
      "albl": [
        "Girls",
        "Original"
      ],
      "norl": [],
      "spel": [
        "Girls Hair Black",
        "Girls Uniform",
        "Girls Long Hair",
        "Girls Eyes Black",
        "Girls Tie Bows"
      ],
      "i_top": 0,
      "i_newest": 0,
      "i_sgg": 0,
      "h_img": 1440,
      "w_img": 1013,
      "date_img_modified": 1645540949974,
      "file_size": "207.24 Kb"
    },
    {
      "id_img": "Original_691375_crop2608_795050511",
      "lik": "UTb0sGqADnbLiHq9qhRMRkSRiLND0Tk7ctN8tpraiidDRUOqYhHyMZSZzFs+pk57k2MmeevepKq8Pbm1WMMuyZVy4706IhQgSYlgwrgVRHU=",
      "thub": "UTb0sGqADnbLiHq9qhRMRkSRiLND0Tk7ctN8tpraiidDRUOqYhHyMZSZzFs+pk57li8P8ezlaIsVQAoYmPpiYZVy4706IhQgSYlgwrgVRHU=",
      "albl": [
        "Girls",
        "Original"
      ],
      "norl": [],
      "spel": [
        "Girls Hair Yellow",
        "Girls Eyes Brown",
        "Girls Long Hair",
        "Girls Hats",
        "Girls Smile",
        "Girls Tie Bows"
      ],
      "i_top": 0,
      "i_newest": 0,
      "i_sgg": 0,
      "h_img": 1080,
      "w_img": 760,
      "date_img_modified": 1645540948738,
      "file_size": "147.76 Kb"
    },
    {
      "id_img": "Original_691224_crop2608_-1431648436",
      "lik": "UTb0sGqADnbLiHq9qhRMRkSRiLND0Tk7ctN8tpraiidWf30H2bwbrHJSoNmju6fwjedHjIMKy9GbVblBniil1JVy4706IhQgSYlgwrgVRHU=",
      "thub": "UTb0sGqADnbLiHq9qhRMRkSRiLND0Tk7ctN8tpraiidWf30H2bwbrHJSoNmju6fw1RZmZmaNfTPotgQN90cT1ZVy4706IhQgSYlgwrgVRHU=",
      "albl": [
        "Girls",
        "Original"
      ],
      "norl": [],
      "spel": [
        "Girls Hair Silver",
        "Girls Hair White",
        "Girls Eyes Red",
        "Girls Long Hair",
        "Girls Water Rain",
        "Girls Kimono Yukata Cheongsam",
        "Girls Tie Bows"
      ],
      "i_top": 0,
      "i_newest": 0,
      "i_sgg": 0,
      "h_img": 1130,
      "w_img": 795,
      "date_img_modified": 1645540948009,
      "file_size": "200.13 Kb"
    },
    {
      "id_img": "Original_691052_crop2608_2024425823",
      "lik": "UTb0sGqADnbLiHq9qhRMRkSRiLND0Tk7ctN8tpraiif5EGfIQgF4dapSJuRFKK3yNdT2X/jWhvfX6LtUmNFs4ZVy4706IhQgSYlgwrgVRHU=",
      "thub": "UTb0sGqADnbLiHq9qhRMRkSRiLND0Tk7ctN8tpraiif5EGfIQgF4dapSJuRFKK3ypxOyQTCHG5Gjoz40FVGmdJVy4706IhQgSYlgwrgVRHU=",
      "albl": [
        "Girls",
        "Original"
      ],
      "norl": [],
      "spel": [
        "Girls Hair Black",
        "Girls Uniform",
        "Girls Short Hair",
        "Girls Eyes Black",
        "Girls Tie Bows"
      ],
      "i_top": 0,
      "i_newest": 0,
      "i_sgg": 0,
      "h_img": 1080,
      "w_img": 760,
      "date_img_modified": 1645540946008,
      "file_size": "107.35 Kb"
    },
    {
      "id_img": "Original_690908_crop2608_1488866398",
      "lik": "UTb0sGqADnbLiHq9qhRMRkSRiLND0Tk7ctN8tpraiidW9lsvK0GnBic+wSM3j8qBfMKX5q/Yj2MCBpHr0xETIZVy4706IhQgSYlgwrgVRHU=",
      "thub": "UTb0sGqADnbLiHq9qhRMRkSRiLND0Tk7ctN8tpraiidW9lsvK0GnBic+wSM3j8qBZ+bhKAGSuhw8KFY7PhgcaZVy4706IhQgSYlgwrgVRHU=",
      "albl": [
        "Girls",
        "Original"
      ],
      "norl": [],
      "spel": [
        "Girls Hair Black",
        "Girls Student",
        "Girls Hoodie",
        "Girls Long Hair",
        "Girls Eyes Black",
        "Girls Tie Bows"
      ],
      "i_top": 0,
      "i_newest": 0,
      "i_sgg": 0,
      "h_img": 1080,
      "w_img": 760,
      "date_img_modified": 1645540943856,
      "file_size": "112.93 Kb"
    },
    {
      "id_img": "Original_690621_crop2608_-1719494808",
      "lik": "UTb0sGqADnbLiHq9qhRMRkSRiLND0Tk7ctN8tpraiifU6YL/BXwIScExAWV7BQNQqv7c9sfQrzKZi1e2vYJroJVy4706IhQgSYlgwrgVRHU=",
      "thub": "UTb0sGqADnbLiHq9qhRMRkSRiLND0Tk7ctN8tpraiifU6YL/BXwIScExAWV7BQNQr3MxlygjmK3BqMx09nn/G5Vy4706IhQgSYlgwrgVRHU=",
      "albl": [
        "Girls",
        "Original"
      ],
      "norl": [],
      "spel": [
        "Girls Eyes Red",
        "Girls Long Hair",
        "Girls Face Masks",
        "Girls Hair Red",
        "Girls Kimono Yukata Cheongsam",
        "Girls Tie Bows"
      ],
      "i_top": 0,
      "i_newest": 0,
      "i_sgg": 0,
      "h_img": 1552,
      "w_img": 1092,
      "date_img_modified": 1645540942290,
      "file_size": "188.72 Kb"
    },
    {
      "id_img": "Original_690459_crop2608_1807730443",
      "lik": "UTb0sGqADnbLiHq9qhRMRkSRiLND0Tk7ctN8tpraiido8Eii0g/qNPFJ/AXRvAg7fsL3W4Vl6hNg3Nkd/KdWfpVy4706IhQgSYlgwrgVRHU=",
      "thub": "UTb0sGqADnbLiHq9qhRMRkSRiLND0Tk7ctN8tpraiido8Eii0g/qNPFJ/AXRvAg7N5QLgEgGUBFYfyZN3SHyCJVy4706IhQgSYlgwrgVRHU=",
      "albl": [
        "Girls",
        "Original"
      ],
      "norl": [],
      "spel": [
        "Girls Eyes Silver",
        "Girls Eyes White",
        "Girls Long Hair",
        "Girls Hair Red",
        "Girls Tie Bows",
        "Girls Witch"
      ],
      "i_top": 0,
      "i_newest": 0,
      "i_sgg": 0,
      "h_img": 1080,
      "w_img": 760,
      "date_img_modified": 1645540941451,
      "file_size": "77.92 Kb"
    },
    {
      "id_img": "Original_690358_crop2608_-1053131063",
      "lik": "UTb0sGqADnbLiHq9qhRMRkSRiLND0Tk7ctN8tpraiicEXsYOaSVx1QS1DlrUA4x8cvvzEn9rEa35n+gsFyLYsZVy4706IhQgSYlgwrgVRHU=",
      "thub": "UTb0sGqADnbLiHq9qhRMRkSRiLND0Tk7ctN8tpraiicEXsYOaSVx1QS1DlrUA4x8hTgKBp5Ijk4VI9Daq3ULtZVy4706IhQgSYlgwrgVRHU=",
      "albl": [
        "Girls",
        "Original"
      ],
      "norl": [
        "bow Clothing",
        "Bunny",
        "Japanese Clothes",
        "Book",
        "Suitcase"
      ],
      "spel": [
        "Girls Hair Orange",
        "Girls Short Hair",
        "Girls Cute Cool",
        "Girls Scarf",
        "Girls Kimono Yukata Cheongsam",
        "Girls Tie Bows",
        "Girls Eyes Blue"
      ],
      "i_top": 0,
      "i_newest": 0,
      "i_sgg": 0,
      "h_img": 1080,
      "w_img": 760,
      "date_img_modified": 1645540941185,
      "file_size": "106.88 Kb"
    },
    {
      "id_img": "Original_689829_crop2608_623392456",
      "lik": "UTb0sGqADnbLiHq9qhRMRkSRiLND0Tk7ctN8tpraiidHFUiwQTAps9v914TE75HRSNIqNQynXuMMG1moPuR53JVy4706IhQgSYlgwrgVRHU=",
      "thub": "UTb0sGqADnbLiHq9qhRMRkSRiLND0Tk7ctN8tpraiidHFUiwQTAps9v914TE75HRE2gmeplEZ19O0V0ulFeqcJVy4706IhQgSYlgwrgVRHU=",
      "albl": [
        "Girls",
        "Original"
      ],
      "norl": [],
      "spel": [
        "Girls Hair Silver",
        "Girls Hair Pink",
        "Girls Long Hair",
        "Girls Cute Cool",
        "Girls Smile",
        "Girls Tie Bows",
        "Girls Eyes Blue"
      ],
      "i_top": 0,
      "i_newest": 0,
      "i_sgg": 0,
      "h_img": 1080,
      "w_img": 760,
      "date_img_modified": 1645540940114,
      "file_size": "111.66 Kb"
    },
    {
      "id_img": "Original_689826_crop2608_395704325",
      "lik": "UTb0sGqADnbLiHq9qhRMRkSRiLND0Tk7ctN8tpraiieztiAgh/DrpMsqN8/hJOXVB7iNViEKl371lC2T3PJt+ZVy4706IhQgSYlgwrgVRHU=",
      "thub": "UTb0sGqADnbLiHq9qhRMRkSRiLND0Tk7ctN8tpraiieztiAgh/DrpMsqN8/hJOXV5PWeGhAV6krX/V7u2IqbhpVy4706IhQgSYlgwrgVRHU=",
      "albl": [
        "Girls",
        "Original"
      ],
      "norl": [],
      "spel": [
        "Girls Hair Black",
        "Girls Uniform",
        "Girls Short Hair",
        "Sad",
        "Girls Eyes Brown",
        "Girls Sad",
        "Girls Water Rain",
        "Girls Tears"
      ],
      "i_top": 0,
      "i_newest": 0,
      "i_sgg": 0,
      "h_img": 1080,
      "w_img": 760,
      "date_img_modified": 1645540939724,
      "file_size": "69.08 Kb"
    },
    {
      "id_img": "Original_689571_crop2608_734864698",
      "lik": "UTb0sGqADnbLiHq9qhRMRkSRiLND0Tk7ctN8tpraiic8dwGqvC3WvUKbNvzu3sI1o9+IelygqXc9HcrebHztepVy4706IhQgSYlgwrgVRHU=",
      "thub": "UTb0sGqADnbLiHq9qhRMRkSRiLND0Tk7ctN8tpraiic8dwGqvC3WvUKbNvzu3sI12U2C8hfxK18rv56g2fXnyJVy4706IhQgSYlgwrgVRHU=",
      "albl": [
        "Girls",
        "Original"
      ],
      "norl": [],
      "spel": [
        "Girls Uniform",
        "Girls Hair Pink",
        "Girls Glasses",
        "Girls Long Hair",
        "Girls Hair Violet",
        "Girls Tie Bows",
        "Girls Eyes Blue"
      ],
      "i_top": 0,
      "i_newest": 0,
      "i_sgg": 0,
      "h_img": 1480,
      "w_img": 1041,
      "date_img_modified": 1645540939535,
      "file_size": "172.11 Kb"
    },
    {
      "id_img": "Original_689570_crop2608_1240423323",
      "lik": "UTb0sGqADnbLiHq9qhRMRkSRiLND0Tk7ctN8tpraiiehtF6yfsoU9KbpR2G29Qp/V7plWoZjdADAftNf58Z3WJVy4706IhQgSYlgwrgVRHU=",
      "thub": "UTb0sGqADnbLiHq9qhRMRkSRiLND0Tk7ctN8tpraiiehtF6yfsoU9KbpR2G29Qp/nuCO4iPARqtreOxzWjKnEJVy4706IhQgSYlgwrgVRHU=",
      "albl": [
        "Girls",
        "Original"
      ],
      "norl": [],
      "spel": [
        "Girls Hair Black",
        "Girls Short Hair",
        "Girls Water Rain",
        "Girls Eyes Black",
        "Girls Tie Bows"
      ],
      "i_top": 0,
      "i_newest": 0,
      "i_sgg": 0,
      "h_img": 1440,
      "w_img": 1013,
      "date_img_modified": 1645540939060,
      "file_size": "135.49 Kb"
    },
    {
      "id_img": "Original_689565_crop2608_1376021309",
      "lik": "UTb0sGqADnbLiHq9qhRMRkSRiLND0Tk7ctN8tpraiiez0BwvxjY0bl1LqRQ+021wClYF5cnhu0A6V8Zt5xL5ZJVy4706IhQgSYlgwrgVRHU=",
      "thub": "UTb0sGqADnbLiHq9qhRMRkSRiLND0Tk7ctN8tpraiiez0BwvxjY0bl1LqRQ+021wrkPpA8B/4e/Yewld2h8g65Vy4706IhQgSYlgwrgVRHU=",
      "albl": [
        "Girls",
        "Original"
      ],
      "norl": [],
      "spel": [
        "Girls Hair Black",
        "Sad",
        "Girls Sad",
        "Girls Long Hair",
        "Girls Tears",
        "Girls Eyes Black"
      ],
      "i_top": 0,
      "i_newest": 0,
      "i_sgg": 0,
      "h_img": 1414,
      "w_img": 995,
      "date_img_modified": 1645540936591,
      "file_size": "119.83 Kb"
    },
    {
      "id_img": "Original_688772_crop2608_46523452",
      "lik": "UTb0sGqADnbLiHq9qhRMRkSRiLND0Tk7ctN8tpraiiehTeO80zKnkgzoiliqw80SeX7nf0LdVHhoj6WfBxN7TZVy4706IhQgSYlgwrgVRHU=",
      "thub": "UTb0sGqADnbLiHq9qhRMRkSRiLND0Tk7ctN8tpraiiehTeO80zKnkgzoiliqw80SRH3NrhiB2le5Xl8ldPpVeZVy4706IhQgSYlgwrgVRHU=",
      "albl": [
        "Girls",
        "Original"
      ],
      "norl": [],
      "spel": [
        "Girls Hair Silver",
        "Girls Eyes Orange",
        "Girls Short Hair",
        "Girls Eyes Red",
        "Girls Hair Grey",
        "Girls Hats"
      ],
      "i_top": 0,
      "i_newest": 0,
      "i_sgg": 0,
      "h_img": 1080,
      "w_img": 760,
      "date_img_modified": 1645540934962,
      "file_size": "80.78 Kb"
    },
    {
      "id_img": "Original_688454_crop2608_22766333",
      "lik": "UTb0sGqADnbLiHq9qhRMRkSRiLND0Tk7ctN8tpraiieHVV4eqvMlUfCeNj8sYrvbUQXgU2YB2uYeuxepv3nrY5Vy4706IhQgSYlgwrgVRHU=",
      "thub": "UTb0sGqADnbLiHq9qhRMRkSRiLND0Tk7ctN8tpraiieHVV4eqvMlUfCeNj8sYrvbdNLAhobOXvaxGR80Ersud5Vy4706IhQgSYlgwrgVRHU=",
      "albl": [
        "Girls",
        "Original"
      ],
      "norl": [
        "Sniper Rifle",
        "Sniper",
        "Blonde"
      ],
      "spel": [
        "Girls Uniform",
        "Girls Hair Yellow",
        "Girls Long Hair",
        "Girls Hats",
        "Girls Eyes Blue"
      ],
      "i_top": 0,
      "i_newest": 0,
      "i_sgg": 0,
      "h_img": 1161,
      "w_img": 817,
      "date_img_modified": 1645540933988,
      "file_size": "96.78 Kb"
    },
    {
      "id_img": "Original_688371_crop2608_1715667447",
      "lik": "UTb0sGqADnbLiHq9qhRMRkSRiLND0Tk7ctN8tpraiifGzgNnQfYDdo2rKXPlUBWUamc3Wyb/suBbR9+/2xT395Vy4706IhQgSYlgwrgVRHU=",
      "thub": "UTb0sGqADnbLiHq9qhRMRkSRiLND0Tk7ctN8tpraiifGzgNnQfYDdo2rKXPlUBWU5nqM99THDrKeKtaDZpaNv5Vy4706IhQgSYlgwrgVRHU=",
      "albl": [
        "Girls",
        "Original"
      ],
      "norl": [
        "Katana",
        "School Uniform"
      ],
      "spel": [
        "Girls Hair Black",
        "Girls Student",
        "Girls Short Hair",
        "Girls Tie Bows",
        "Girls Eyes Blue"
      ],
      "i_top": 0,
      "i_newest": 0,
      "i_sgg": 0,
      "h_img": 1640,
      "w_img": 1154,
      "date_img_modified": 1645540933535,
      "file_size": "129.65 Kb"
    },
    {
      "id_img": "Original_688298_crop2608_-1845996530",
      "lik": "UTb0sGqADnbLiHq9qhRMRkSRiLND0Tk7ctN8tpraiifAcUcHw0qj9brgVOROCuJ6/iDq/04P67lc8TKXtTQblZVy4706IhQgSYlgwrgVRHU=",
      "thub": "UTb0sGqADnbLiHq9qhRMRkSRiLND0Tk7ctN8tpraiifAcUcHw0qj9brgVOROCuJ6R+VHr2g60KyNIikBSQXvZZVy4706IhQgSYlgwrgVRHU=",
      "albl": [
        "Girls",
        "Original"
      ],
      "norl": [
        "Blonde",
        "Petal",
        "Violin",
        "Violinist"
      ],
      "spel": [
        "Girls Hair Silver",
        "Girls Hair White",
        "Girls Uniform",
        "Girls Short Hair",
        "Girls Music",
        "Girls Tie Bows"
      ],
      "i_top": 0,
      "i_newest": 0,
      "i_sgg": 0,
      "h_img": 2121,
      "w_img": 1493,
      "date_img_modified": 1645540933035,
      "file_size": "273.75 Kb"
    },
    {
      "id_img": "Original_688188_crop2608_-607666857",
      "lik": "UTb0sGqADnbLiHq9qhRMRkSRiLND0Tk7ctN8tpraiifyI3RnUDir46bC2oVHtTB6H8gf9tK7UrChn4E5j0anb5Vy4706IhQgSYlgwrgVRHU=",
      "thub": "UTb0sGqADnbLiHq9qhRMRkSRiLND0Tk7ctN8tpraiifyI3RnUDir46bC2oVHtTB6nu8FkJSiQTr4q1jmGrCkq5Vy4706IhQgSYlgwrgVRHU=",
      "albl": [
        "Girls",
        "Original"
      ],
      "norl": [],
      "spel": [
        "Girls Hair Black",
        "Girls Uniform",
        "Girls Eyes Brown",
        "Girls Long Hair",
        "Girls Hats",
        "Girls Scarf",
        "Girls Tie Bows"
      ],
      "i_top": 0,
      "i_newest": 0,
      "i_sgg": 0,
      "h_img": 1390,
      "w_img": 978,
      "date_img_modified": 1645540932351,
      "file_size": "103.55 Kb"
    },
    {
      "id_img": "Original_687926_crop2608_-1194541686",
      "lik": "UTb0sGqADnbLiHq9qhRMRkSRiLND0Tk7ctN8tpraiicT0T1aSU1f/1q+qcwjgSBGHye0KcX1ywtwyicg+w4xy5Vy4706IhQgSYlgwrgVRHU=",
      "thub": "UTb0sGqADnbLiHq9qhRMRkSRiLND0Tk7ctN8tpraiicT0T1aSU1f/1q+qcwjgSBGK/9FfeOPlCpwR7Nig43F1ZVy4706IhQgSYlgwrgVRHU=",
      "albl": [
        "Girls",
        "Original"
      ],
      "norl": [],
      "spel": [
        "Girls Hair Yellow",
        "Girls Short Hair",
        "Girls Long Hair",
        "Girls Water Rain",
        "Girls Eyes Black",
        "Girls Kimono Yukata Cheongsam",
        "Girls Tie Bows",
        "Girls Eyes Blue",
        "Girls Hair Brow"
      ],
      "i_top": 0,
      "i_newest": 0,
      "i_sgg": 0,
      "h_img": 1414,
      "w_img": 995,
      "date_img_modified": 1645540930425,
      "file_size": "187.61 Kb"
    },
    {
      "id_img": "Original_687926_crop2608_-551808568",
      "lik": "UTb0sGqADnbLiHq9qhRMRkSRiLND0Tk7ctN8tpraiiegTEyFcwf5Cp5Ie/iFZohyMhNP4qXd/gvZlRrI2LPjdZVy4706IhQgSYlgwrgVRHU=",
      "thub": "UTb0sGqADnbLiHq9qhRMRkSRiLND0Tk7ctN8tpraiiegTEyFcwf5Cp5Ie/iFZohyLvJEovk0rKXV7wk0B4oMr5Vy4706IhQgSYlgwrgVRHU=",
      "albl": [
        "Girls",
        "Original"
      ],
      "norl": [],
      "spel": [
        "Girls Long Hair",
        "Girls Water Rain",
        "Girls Smile",
        "Girls Eyes Black",
        "Girls Kimono Yukata Cheongsam",
        "Girls Tie Bows",
        "Girls Hair Brow"
      ],
      "i_top": 0,
      "i_newest": 0,
      "i_sgg": 0,
      "h_img": 1414,
      "w_img": 995,
      "date_img_modified": 1645540930356,
      "file_size": "156.93 Kb"
    },
    {
      "id_img": "Original_687925_crop2608_-2059360377",
      "lik": "UTb0sGqADnbLiHq9qhRMRkSRiLND0Tk7ctN8tpraiif9TKCSenI1+JYJDMG/fvQKedOOf9xPPn5oinBBX5aieJVy4706IhQgSYlgwrgVRHU=",
      "thub": "UTb0sGqADnbLiHq9qhRMRkSRiLND0Tk7ctN8tpraiif9TKCSenI1+JYJDMG/fvQKrOeNFWkhxhxqeEKPJ19MaZVy4706IhQgSYlgwrgVRHU=",
      "albl": [
        "Girls",
        "Original"
      ],
      "norl": [],
      "spel": [
        "Girls Hair Black",
        "Girls Student",
        "Girls Long Hair",
        "Girls Tie Bows"
      ],
      "i_top": 0,
      "i_newest": 0,
      "i_sgg": 0,
      "h_img": 1217,
      "w_img": 856,
      "date_img_modified": 1645540929914,
      "file_size": "112.25 Kb"
    },
    {
      "id_img": "Original_687714_crop2608_-669907891",
      "lik": "UTb0sGqADnbLiHq9qhRMRkSRiLND0Tk7ctN8tpraiidhP5bHR7O0hYP1X4PNftvl6mCUUv/j1oy3eQ6z2gQpnJVy4706IhQgSYlgwrgVRHU=",
      "thub": "UTb0sGqADnbLiHq9qhRMRkSRiLND0Tk7ctN8tpraiidhP5bHR7O0hYP1X4PNftvlbm1qqpSwARrt57CiyDWMzZVy4706IhQgSYlgwrgVRHU=",
      "albl": [
        "Girls",
        "Original"
      ],
      "norl": [
        "Water",
        "Sunset",
        "Camera"
      ],
      "spel": [
        "Girls Long Hair",
        "Girls Smile",
        "Girls Eyes Black",
        "Girls Tie Bows",
        "Girls Hair Brow"
      ],
      "i_top": 0,
      "i_newest": 0,
      "i_sgg": 0,
      "h_img": 1200,
      "w_img": 844,
      "date_img_modified": 1645540929664,
      "file_size": "90.55 Kb"
    },
    {
      "id_img": "Original_687714_crop2608_-1468030107",
      "lik": "UTb0sGqADnbLiHq9qhRMRkSRiLND0Tk7ctN8tpraiidmDWf1/f8TgvXrGKX44DwLSS2vIw5pKyvIC7HGRjX0M5Vy4706IhQgSYlgwrgVRHU=",
      "thub": "UTb0sGqADnbLiHq9qhRMRkSRiLND0Tk7ctN8tpraiidmDWf1/f8TgvXrGKX44DwL0WlIIg3G43OLe3kl1bQfxJVy4706IhQgSYlgwrgVRHU=",
      "albl": [
        "Girls",
        "Original"
      ],
      "norl": [
        "Water",
        "Sunset",
        "Camera"
      ],
      "spel": [
        "Girls Hair Black",
        "Girls Eyes Orange",
        "Girls Hoodie",
        "Girls Long Hair",
        "Girls Cute Cool",
        "Girls Tie Bows"
      ],
      "i_top": 0,
      "i_newest": 0,
      "i_sgg": 0,
      "h_img": 1200,
      "w_img": 844,
      "date_img_modified": 1645540929598,
      "file_size": "119.09 Kb"
    },
    {
      "id_img": "Original_687713_crop2608_1319385380",
      "lik": "UTb0sGqADnbLiHq9qhRMRkSRiLND0Tk7ctN8tpraiifuMfzgp0/ibDi6/6G5zhJHjd8Y7brtJmBnlWC5yCFO5pVy4706IhQgSYlgwrgVRHU=",
      "thub": "UTb0sGqADnbLiHq9qhRMRkSRiLND0Tk7ctN8tpraiifuMfzgp0/ibDi6/6G5zhJHg7pNrOuNGRvQRRQk0jhx9pVy4706IhQgSYlgwrgVRHU=",
      "albl": [
        "Girls",
        "Original"
      ],
      "norl": [],
      "spel": [
        "Girls Hair Silver",
        "Girls Hair White",
        "Girls Uniform",
        "Girls Short Hair",
        "Girls Hair Grey",
        "Girls Long Hair",
        "Girls Eyes Black",
        "Girls Tie Bows"
      ],
      "i_top": 0,
      "i_newest": 0,
      "i_sgg": 0,
      "h_img": 1080,
      "w_img": 760,
      "date_img_modified": 1645540929284,
      "file_size": "134.72 Kb"
    },
    {
      "id_img": "Original_687711_crop2608_-1695718238",
      "lik": "UTb0sGqADnbLiHq9qhRMRkSRiLND0Tk7ctN8tpraiidWsCi7k40bY/3aZcEmoYUQrJ6qF2J6xtaqIFxX76i+2JVy4706IhQgSYlgwrgVRHU=",
      "thub": "UTb0sGqADnbLiHq9qhRMRkSRiLND0Tk7ctN8tpraiidWsCi7k40bY/3aZcEmoYUQZC3ZAY8+lANUsDByiJDWypVy4706IhQgSYlgwrgVRHU=",
      "albl": [
        "Girls",
        "Original"
      ],
      "norl": [],
      "spel": [
        "Girls Hair Silver",
        "Girls Uniform",
        "Girls Long Hair",
        "Girls Scarf",
        "Girls Tie Bows",
        "Girls Eyes Blue"
      ],
      "i_top": 0,
      "i_newest": 0,
      "i_sgg": 0,
      "h_img": 1200,
      "w_img": 844,
      "date_img_modified": 1645540928769,
      "file_size": "133.27 Kb"
    },
    {
      "id_img": "Original_687709_crop2608_-2009671477",
      "lik": "UTb0sGqADnbLiHq9qhRMRkSRiLND0Tk7ctN8tpraiietGFzllEBZSeXDdxQz9APY+19FgopL2O6I3ozLRBLXe5Vy4706IhQgSYlgwrgVRHU=",
      "thub": "UTb0sGqADnbLiHq9qhRMRkSRiLND0Tk7ctN8tpraiietGFzllEBZSeXDdxQz9APY5TKJUOHyQS8FVKXnjIpKLZVy4706IhQgSYlgwrgVRHU=",
      "albl": [
        "Girls",
        "Original"
      ],
      "norl": [],
      "spel": [
        "Girls Uniform",
        "Girls Short Hair",
        "Girls Eyes Brown",
        "Girls Hair Brow"
      ],
      "i_top": 0,
      "i_newest": 0,
      "i_sgg": 0,
      "h_img": 1250,
      "w_img": 880,
      "date_img_modified": 1645540928333,
      "file_size": "135.56 Kb"
    },
    {
      "id_img": "Original_687411_crop2608_-812003278",
      "lik": "UTb0sGqADnbLiHq9qhRMRkSRiLND0Tk7ctN8tpraiidDmYV8wPGDA0BwKDm3ubIzg3DAdePKq9yjrp01KvXHjpVy4706IhQgSYlgwrgVRHU=",
      "thub": "UTb0sGqADnbLiHq9qhRMRkSRiLND0Tk7ctN8tpraiidDmYV8wPGDA0BwKDm3ubIzjiZAGhzHzlC/zLWMUCG5sJVy4706IhQgSYlgwrgVRHU=",
      "albl": [
        "Girls",
        "Original"
      ],
      "norl": [
        "Room",
        "Cat",
        "Cup",
        "Cake"
      ],
      "spel": [
        "Girls Hair Pink",
        "Girls Long Hair",
        "Girls Hats",
        "Girls Hair Violet",
        "Girls Tie Bows",
        "Girls Eyes Blue"
      ],
      "i_top": 0,
      "i_newest": 0,
      "i_sgg": 0,
      "h_img": 1080,
      "w_img": 760,
      "date_img_modified": 1645540927155,
      "file_size": "150.96 Kb"
    },
    {
      "id_img": "Original_687344_crop2608_177063166",
      "lik": "UTb0sGqADnbLiHq9qhRMRkSRiLND0Tk7ctN8tpraiiciWXrrIDNmGl9lUB7TIoDAYDWhf0O47kZQI+8CcY10x5Vy4706IhQgSYlgwrgVRHU=",
      "thub": "UTb0sGqADnbLiHq9qhRMRkSRiLND0Tk7ctN8tpraiiciWXrrIDNmGl9lUB7TIoDAfSLeIutMGoApC9VRnh9Vx5Vy4706IhQgSYlgwrgVRHU=",
      "albl": [
        "Girls",
        "Original"
      ],
      "norl": [
        "Fantasy",
        "Shop"
      ],
      "spel": [
        "Girls Hair Yellow",
        "Girls Horns",
        "Girls Long Hair",
        "Girls Ears Neko",
        "Girls Eyes Black",
        "Girls Tie Bows"
      ],
      "i_top": 0,
      "i_newest": 0,
      "i_sgg": 0,
      "h_img": 1080,
      "w_img": 760,
      "date_img_modified": 1645540926896,
      "file_size": "154.89 Kb"
    },
    {
      "id_img": "Original_686324_crop2608_-2099763423",
      "lik": "UTb0sGqADnbLiHq9qhRMRkSRiLND0Tk7ctN8tpraiieh8xorGBbukW3Gr3QM7nKjhRPEiUsZPoWFI/aIwTteTJVy4706IhQgSYlgwrgVRHU=",
      "thub": "UTb0sGqADnbLiHq9qhRMRkSRiLND0Tk7ctN8tpraiieh8xorGBbukW3Gr3QM7nKjy+Jq4Que57SdJJnoZQNbcJVy4706IhQgSYlgwrgVRHU=",
      "albl": [
        "Girls",
        "Original"
      ],
      "norl": [
        "Winter",
        "Scarf",
        "Snowfall"
      ],
      "spel": [
        "Girls Short Hair",
        "Girls Hair Pink",
        "Girls Eyes Red",
        "Girls Ears Neko",
        "Girls Scarf",
        "Girls Tie Bows"
      ],
      "i_top": 0,
      "i_newest": 0,
      "i_sgg": 0,
      "h_img": 4851,
      "w_img": 3415,
      "date_img_modified": 1645540925002,
      "file_size": "1016.96 Kb"
    },
    {
      "id_img": "Original_685854_crop2608_-162712412",
      "lik": "UTb0sGqADnbLiHq9qhRMRkSRiLND0Tk7ctN8tpraiieeixhFk+86lwZI6S/EezuqSp8lhYMXqKMEpA0Tcy1x4pVy4706IhQgSYlgwrgVRHU=",
      "thub": "UTb0sGqADnbLiHq9qhRMRkSRiLND0Tk7ctN8tpraiieeixhFk+86lwZI6S/EezuqhS6EWPj3RLbhlLR9AaiT8pVy4706IhQgSYlgwrgVRHU=",
      "albl": [
        "Girls",
        "Original"
      ],
      "norl": [],
      "spel": [
        "Girls Hair Black",
        "Girls Short Hair",
        "Girls Kimono Yukata Cheongsam",
        "Girls Tie Bows"
      ],
      "i_top": 0,
      "i_newest": 0,
      "i_sgg": 0,
      "h_img": 1753,
      "w_img": 1234,
      "date_img_modified": 1645540922539,
      "file_size": "201.13 Kb"
    },
    {
      "id_img": "Original_685119_crop2608_-55984538",
      "lik": "UTb0sGqADnbLiHq9qhRMRkSRiLND0Tk7ctN8tpraiidEwn1jnWY+dILbjPP54PdzUMqQ8MFQhKJadouywDe0hpVy4706IhQgSYlgwrgVRHU=",
      "thub": "UTb0sGqADnbLiHq9qhRMRkSRiLND0Tk7ctN8tpraiidEwn1jnWY+dILbjPP54Pdz8ZQF5KK7QpquL9BxTonXU5Vy4706IhQgSYlgwrgVRHU=",
      "albl": [
        "Girls",
        "Original"
      ],
      "norl": [],
      "spel": [
        "Girls Eyes Pink",
        "Girls Short Hair",
        "Girls Hair Blue"
      ],
      "i_top": 0,
      "i_newest": 0,
      "i_sgg": 0,
      "h_img": 1378,
      "w_img": 970,
      "date_img_modified": 1645540921682,
      "file_size": "220.34 Kb"
    },
    {
      "id_img": "Original_684892_crop2608_72086911",
      "lik": "UTb0sGqADnbLiHq9qhRMRkSRiLND0Tk7ctN8tpraiidOq6Ai6/v0vejsp4vs6P/yondTnHQZU8VwIZreknO6+5Vy4706IhQgSYlgwrgVRHU=",
      "thub": "UTb0sGqADnbLiHq9qhRMRkSRiLND0Tk7ctN8tpraiidOq6Ai6/v0vejsp4vs6P/yvPM1G1lAidqG05uKYjAZn5Vy4706IhQgSYlgwrgVRHU=",
      "albl": [
        "Girls",
        "Original"
      ],
      "norl": [
        "Bride"
      ],
      "spel": [
        "Girls Short Hair",
        "Girls Eyes Blue",
        "Girls Wedding",
        "Girls Hair Brow"
      ],
      "i_top": 0,
      "i_newest": 0,
      "i_sgg": 0,
      "h_img": 1799,
      "w_img": 1266,
      "date_img_modified": 1645540920356,
      "file_size": "254.59 Kb"
    },
    {
      "id_img": "Original_684744_crop2608_-207181555",
      "lik": "UTb0sGqADnbLiHq9qhRMRkSRiLND0Tk7ctN8tpraiieIEWf4gy1GXgpMD5FXaofJg+HnNQEzIPZ7wnDk7JMGfZVy4706IhQgSYlgwrgVRHU=",
      "thub": "UTb0sGqADnbLiHq9qhRMRkSRiLND0Tk7ctN8tpraiieIEWf4gy1GXgpMD5FXaofJQ3n+ClP13TBhY+8+eUB225Vy4706IhQgSYlgwrgVRHU=",
      "albl": [
        "Girls",
        "Original"
      ],
      "norl": [
        "Cloud"
      ],
      "spel": [
        "Girls Hair Black",
        "Girls Eyes Red",
        "Girls Hair Grey",
        "Girls Long Hair",
        "Girls Tie Bows"
      ],
      "i_top": 0,
      "i_newest": 0,
      "i_sgg": 0,
      "h_img": 1200,
      "w_img": 844,
      "date_img_modified": 1645540919902,
      "file_size": "102.68 Kb"
    },
    {
      "id_img": "Original_684744_crop2608_-8415579",
      "lik": "UTb0sGqADnbLiHq9qhRMRkSRiLND0Tk7ctN8tpraiicdFSPgjdjj1+KGCju34KfgfEJjxvkHFrU2RuUSTTCYsZVy4706IhQgSYlgwrgVRHU=",
      "thub": "UTb0sGqADnbLiHq9qhRMRkSRiLND0Tk7ctN8tpraiicdFSPgjdjj1+KGCju34KfgBmJI0ooTsEbcyejTbff0p5Vy4706IhQgSYlgwrgVRHU=",
      "albl": [
        "Girls",
        "Original"
      ],
      "norl": [
        "Cloud"
      ],
      "spel": [
        "Girls Hair Black",
        "Girls Eyes Red",
        "Girls Hair Grey",
        "Girls Long Hair",
        "Girls Water Rain",
        "Girls Tie Bows"
      ],
      "i_top": 0,
      "i_newest": 0,
      "i_sgg": 0,
      "h_img": 1200,
      "w_img": 844,
      "date_img_modified": 1645540919834,
      "file_size": "105.09 Kb"
    },
    {
      "id_img": "Original_684733_crop2608_-1209174739",
      "lik": "UTb0sGqADnbLiHq9qhRMRkSRiLND0Tk7ctN8tpraiidRf7P3H0G9+T5ING3Aqf/qgGdnbxUX4dgeVF7xrGk8ApVy4706IhQgSYlgwrgVRHU=",
      "thub": "UTb0sGqADnbLiHq9qhRMRkSRiLND0Tk7ctN8tpraiidRf7P3H0G9+T5ING3Aqf/qR7SMZ5usN+8pzeVzChxh3JVy4706IhQgSYlgwrgVRHU=",
      "albl": [
        "Girls",
        "Original"
      ],
      "norl": [
        "Aqua Eyes",
        "Cute"
      ],
      "spel": [
        "Girls Sharp Canine Tooth",
        "Girls Short Hair",
        "Girls Hair Pink",
        "Girls Ears Neko",
        "Girls Smile",
        "Girls Tie Bows",
        "Girls Eyes Blue"
      ],
      "i_top": 0,
      "i_newest": 0,
      "i_sgg": 0,
      "h_img": 1536,
      "w_img": 1081,
      "date_img_modified": 1645540919209,
      "file_size": "126.94 Kb"
    },
    {
      "id_img": "Original_684733_crop2608_-1005433211",
      "lik": "UTb0sGqADnbLiHq9qhRMRkSRiLND0Tk7ctN8tpraiifLPsW/XN8+suURYtQAZcQntPz3XfLiAsXDfYnB2e5c+ZVy4706IhQgSYlgwrgVRHU=",
      "thub": "UTb0sGqADnbLiHq9qhRMRkSRiLND0Tk7ctN8tpraiifLPsW/XN8+suURYtQAZcQn92Byta47+6J+61+BqIjWnJVy4706IhQgSYlgwrgVRHU=",
      "albl": [
        "Girls",
        "Original"
      ],
      "norl": [
        "Aqua Eyes",
        "Cute"
      ],
      "spel": [
        "Girls Hair Yellow",
        "Girls Eyes Yellow",
        "Girls Long Hair",
        "Girls Tie Bows"
      ],
      "i_top": 0,
      "i_newest": 0,
      "i_sgg": 0,
      "h_img": 1536,
      "w_img": 1081,
      "date_img_modified": 1645540919127,
      "file_size": "155.17 Kb"
    },
    {
      "id_img": "Original_684733_crop2608_-650635880",
      "lik": "UTb0sGqADnbLiHq9qhRMRkSRiLND0Tk7ctN8tpraiicHb8Djja/+W4nU2xbxPCCRw4cdyl6IbskNDPBNmYngpZVy4706IhQgSYlgwrgVRHU=",
      "thub": "UTb0sGqADnbLiHq9qhRMRkSRiLND0Tk7ctN8tpraiicHb8Djja/+W4nU2xbxPCCRbhEIyMiNs5Y4HAYhUGUFJJVy4706IhQgSYlgwrgVRHU=",
      "albl": [
        "Girls",
        "Original"
      ],
      "norl": [
        "Aqua Eyes",
        "Cute"
      ],
      "spel": [
        "Girls Hair Silver",
        "Sad",
        "Girls Eyes Yellow",
        "Girls Sad",
        "Girls Long Hair",
        "Girls Cute Cool",
        "Girls Ears Neko",
        "Girls Tie Bows"
      ],
      "i_top": 0,
      "i_newest": 0,
      "i_sgg": 0,
      "h_img": 1536,
      "w_img": 1081,
      "date_img_modified": 1645540919053,
      "file_size": "153.70 Kb"
    },
    {
      "id_img": "Original_684732_crop2608_1781982276",
      "lik": "UTb0sGqADnbLiHq9qhRMRkSRiLND0Tk7ctN8tpraiiejLjUKddEXk82dxgUxIs0L9bDhAX0pyDsZbyCVwVWGcZVy4706IhQgSYlgwrgVRHU=",
      "thub": "UTb0sGqADnbLiHq9qhRMRkSRiLND0Tk7ctN8tpraiiejLjUKddEXk82dxgUxIs0LVwhq4QdBMvd1Urj4FOnhupVy4706IhQgSYlgwrgVRHU=",
      "albl": [
        "Girls",
        "Original"
      ],
      "norl": [
        "Blonde",
        "Cute"
      ],
      "spel": [
        "Girls Hair Yellow",
        "Girls Long Hair",
        "Girls Cute Cool",
        "Girls Hats",
        "Girls Smile",
        "Girls Tie Bows"
      ],
      "i_top": 0,
      "i_newest": 0,
      "i_sgg": 0,
      "h_img": 1200,
      "w_img": 844,
      "date_img_modified": 1645540918503,
      "file_size": "156.58 Kb"
    },
    {
      "id_img": "Original_684729_crop2608_-1455111002",
      "lik": "UTb0sGqADnbLiHq9qhRMRkSRiLND0Tk7ctN8tpraiidqbEjO1il9onLEY0pSO82pqx2IsFxxPoLbYnQNEVayQJVy4706IhQgSYlgwrgVRHU=",
      "thub": "UTb0sGqADnbLiHq9qhRMRkSRiLND0Tk7ctN8tpraiidqbEjO1il9onLEY0pSO82pBIBc/5nyddaaHXF1mJOpc5Vy4706IhQgSYlgwrgVRHU=",
      "albl": [
        "Girls",
        "Original"
      ],
      "norl": [
        "Food"
      ],
      "spel": [
        "Girls Hair Pink",
        "Girls Long Hair",
        "Girls Cute Cool",
        "Girls Eyes Violet",
        "Girls Tie Bows"
      ],
      "i_top": 0,
      "i_newest": 0,
      "i_sgg": 0,
      "h_img": 1200,
      "w_img": 844,
      "date_img_modified": 1645540918178,
      "file_size": "111.83 Kb"
    },
    {
      "id_img": "Original_684723_crop2608_-494899034",
      "lik": "UTb0sGqADnbLiHq9qhRMRkSRiLND0Tk7ctN8tpraiiePBsvOdB88o/KH0JFzutPBr7g2UOI8GKCi8FyQYJ86X5Vy4706IhQgSYlgwrgVRHU=",
      "thub": "UTb0sGqADnbLiHq9qhRMRkSRiLND0Tk7ctN8tpraiiePBsvOdB88o/KH0JFzutPBOCOKVY2pm/zdTirHt41bBZVy4706IhQgSYlgwrgVRHU=",
      "albl": [
        "Girls",
        "Original"
      ],
      "norl": [
        "Aqua Eyes",
        "School Uniform"
      ],
      "spel": [
        "Girls Hair Black",
        "Girls Student",
        "Girls Long Hair",
        "Girls Cute Cool",
        "Girls Eyes Black",
        "Girls Tie Bows",
        "Girls Eyes Blue"
      ],
      "i_top": 0,
      "i_newest": 0,
      "i_sgg": 0,
      "h_img": 1080,
      "w_img": 760,
      "date_img_modified": 1645540917811,
      "file_size": "119.61 Kb"
    },
    {
      "id_img": "Original_684693_crop2608_-1126980674",
      "lik": "UTb0sGqADnbLiHq9qhRMRkSRiLND0Tk7ctN8tpraiid/O4kKgfIUDuZErQv68/mWnpqAkun8yUoIe23mIO1tM5Vy4706IhQgSYlgwrgVRHU=",
      "thub": "UTb0sGqADnbLiHq9qhRMRkSRiLND0Tk7ctN8tpraiid/O4kKgfIUDuZErQv68/mWb9BpFJ5M2U91XnCOUy9fdZVy4706IhQgSYlgwrgVRHU=",
      "albl": [
        "Girls",
        "Original"
      ],
      "norl": [
        "Blonde",
        "bow Clothing"
      ],
      "spel": [
        "Girls Hair Yellow",
        "Girls Short Hair",
        "Girls Cute Cool",
        "Girls Maid",
        "Girls Smile",
        "Girls Tie Bows",
        "Girls Eyes Blue"
      ],
      "i_top": 0,
      "i_newest": 0,
      "i_sgg": 0,
      "h_img": 1200,
      "w_img": 844,
      "date_img_modified": 1645540917521,
      "file_size": "118.01 Kb"
    },
    {
      "id_img": "Original_684693_crop2608_-896572143",
      "lik": "UTb0sGqADnbLiHq9qhRMRkSRiLND0Tk7ctN8tpraiifuF21qDL+J6rDi2YvR12pc1eHjg3B/D064Zd5y/Ywsi5Vy4706IhQgSYlgwrgVRHU=",
      "thub": "UTb0sGqADnbLiHq9qhRMRkSRiLND0Tk7ctN8tpraiifuF21qDL+J6rDi2YvR12pcYRtgEiO8LZtCeq97Rccs7ZVy4706IhQgSYlgwrgVRHU=",
      "albl": [
        "Girls",
        "Original"
      ],
      "norl": [
        "Blonde",
        "bow Clothing"
      ],
      "spel": [
        "Girls Uniform",
        "Girls Hair Yellow",
        "Girls Short Hair",
        "Girls Smile",
        "Girls Tie Bows",
        "Girls Eyes Blue"
      ],
      "i_top": 0,
      "i_newest": 0,
      "i_sgg": 0,
      "h_img": 1200,
      "w_img": 844,
      "date_img_modified": 1645540917462,
      "file_size": "129.58 Kb"
    },
    {
      "id_img": "Original_684691_crop2608_767852950",
      "lik": "UTb0sGqADnbLiHq9qhRMRkSRiLND0Tk7ctN8tpraiicDPcirGQhsXokDWFss3iTBkGiu8q0+Xo++7XtTO94QtJVy4706IhQgSYlgwrgVRHU=",
      "thub": "UTb0sGqADnbLiHq9qhRMRkSRiLND0Tk7ctN8tpraiicDPcirGQhsXokDWFss3iTBml8fDZ8KQ/vnXPMH80zdJZVy4706IhQgSYlgwrgVRHU=",
      "albl": [
        "Girls",
        "Original"
      ],
      "norl": [
        "Blonde",
        "Twintails",
        "Lying Down",
        "Cute",
        "Stuffed Animal"
      ],
      "spel": [
        "Girls Hair Yellow",
        "Sad",
        "Girls Sad",
        "Girls Long Hair",
        "Girls Tie Bows",
        "Girls Eyes Blue"
      ],
      "i_top": 0,
      "i_newest": 0,
      "i_sgg": 0,
      "h_img": 1200,
      "w_img": 844,
      "date_img_modified": 1645540917231,
      "file_size": "145.61 Kb"
    },
    {
      "id_img": "Original_684691_crop2608_152883004",
      "lik": "UTb0sGqADnbLiHq9qhRMRkSRiLND0Tk7ctN8tpraiidcuCt+uzqg4BLmWURAPn1uCLMpvS3Awl9t1wT/44QI8ZVy4706IhQgSYlgwrgVRHU=",
      "thub": "UTb0sGqADnbLiHq9qhRMRkSRiLND0Tk7ctN8tpraiidcuCt+uzqg4BLmWURAPn1uE897U4wAVXev8c51j+DIxJVy4706IhQgSYlgwrgVRHU=",
      "albl": [
        "Girls",
        "Original"
      ],
      "norl": [
        "Blonde",
        "Twintails",
        "Lying Down",
        "Cute",
        "Stuffed Animal"
      ],
      "spel": [
        "Girls Hair Yellow",
        "Sad",
        "Girls Sad",
        "Girls Long Hair",
        "Girls Tie Bows",
        "Girls Eyes Blue"
      ],
      "i_top": 0,
      "i_newest": 0,
      "i_sgg": 0,
      "h_img": 1200,
      "w_img": 844,
      "date_img_modified": 1645540917158,
      "file_size": "143.94 Kb"
    },
    {
      "id_img": "Original_684686_crop2608_1027475312",
      "lik": "UTb0sGqADnbLiHq9qhRMRkSRiLND0Tk7ctN8tpraiif6j93Qv01ynG4ftjwAZ247MpFACkSNxJtKA8Gk8ntNKJVy4706IhQgSYlgwrgVRHU=",
      "thub": "UTb0sGqADnbLiHq9qhRMRkSRiLND0Tk7ctN8tpraiif6j93Qv01ynG4ftjwAZ247rn/v3Tz8ZbpuzWOcSpAhL5Vy4706IhQgSYlgwrgVRHU=",
      "albl": [
        "Girls",
        "Original"
      ],
      "norl": [
        "Butterfly",
        "Cute"
      ],
      "spel": [
        "Girls Hair Black",
        "Girls Short Hair",
        "Girls Eyes Red",
        "Girls Hair Grey",
        "Girls Tie Bows"
      ],
      "i_top": 0,
      "i_newest": 0,
      "i_sgg": 0,
      "h_img": 1200,
      "w_img": 844,
      "date_img_modified": 1645540916892,
      "file_size": "138.17 Kb"
    },
    {
      "id_img": "Original_684575_crop2608_1555881601",
      "lik": "UTb0sGqADnbLiHq9qhRMRkSRiLND0Tk7ctN8tpraiifc9bjkHUAcaq88riTLpzbppQlLlteT5b8N8Pi4PUcRD5Vy4706IhQgSYlgwrgVRHU=",
      "thub": "UTb0sGqADnbLiHq9qhRMRkSRiLND0Tk7ctN8tpraiifc9bjkHUAcaq88riTLpzbpnCeYhLSi1VBjqkYy5guiOJVy4706IhQgSYlgwrgVRHU=",
      "albl": [
        "Girls",
        "Original"
      ],
      "norl": [
        "Blonde",
        "Doll",
        "Cute"
      ],
      "spel": [
        "Girls Hair Yellow",
        "Girls Long Hair",
        "Girls Cute Cool",
        "Girls Tie Bows",
        "Girls Eyes Blue"
      ],
      "i_top": 0,
      "i_newest": 0,
      "i_sgg": 0,
      "h_img": 1600,
      "w_img": 1126,
      "date_img_modified": 1645540915983,
      "file_size": "180.75 Kb"
    },
    {
      "id_img": "Original_684478_crop2608_430260035",
      "lik": "UTb0sGqADnbLiHq9qhRMRkSRiLND0Tk7ctN8tpraiifSxbnYknTAE5wCSMKLk/yakM+LTcppNFf0oNIjDlzLnpVy4706IhQgSYlgwrgVRHU=",
      "thub": "UTb0sGqADnbLiHq9qhRMRkSRiLND0Tk7ctN8tpraiifSxbnYknTAE5wCSMKLk/yavDkrBV1UMDrW10Ww/010ApVy4706IhQgSYlgwrgVRHU=",
      "albl": [
        "Girls",
        "Original"
      ],
      "norl": [],
      "spel": [
        "Girls Hair Yellow",
        "Girls Long Hair",
        "Girls Smile",
        "Girls Tie Bows",
        "Girls Eyes Blue"
      ],
      "i_top": 0,
      "i_newest": 0,
      "i_sgg": 0,
      "h_img": 1400,
      "w_img": 985,
      "date_img_modified": 1645540914919,
      "file_size": "157.86 Kb"
    },
    {
      "id_img": "Original_683689_crop2608_836002118",
      "lik": "UTb0sGqADnbLiHq9qhRMRkSRiLND0Tk7ctN8tpraiieYEWaQSIZRF248G1gqBIvs/nLu3yk1S5pJyWbnequEhZVy4706IhQgSYlgwrgVRHU=",
      "thub": "UTb0sGqADnbLiHq9qhRMRkSRiLND0Tk7ctN8tpraiieYEWaQSIZRF248G1gqBIvsgkcAKSFtfOXMCWEPEsUzZpVy4706IhQgSYlgwrgVRHU=",
      "albl": [
        "Girls",
        "Original"
      ],
      "norl": [],
      "spel": [
        "Girls Hair Silver",
        "Girls Student",
        "Girls Hair White",
        "Girls Eyes Yellow",
        "Girls Long Hair",
        "Girls Cute Cool",
        "Girls Tie Bows"
      ],
      "i_top": 0,
      "i_newest": 0,
      "i_sgg": 0,
      "h_img": 1200,
      "w_img": 844,
      "date_img_modified": 1645540914264,
      "file_size": "118.88 Kb"
    },
    {
      "id_img": "Original_683457_crop2608_940848933",
      "lik": "UTb0sGqADnbLiHq9qhRMRkSRiLND0Tk7ctN8tpraiicr1w3eaE1hu+8LXRYpFQTi8UD77sqwsrR0rfVTvahW6pVy4706IhQgSYlgwrgVRHU=",
      "thub": "UTb0sGqADnbLiHq9qhRMRkSRiLND0Tk7ctN8tpraiicr1w3eaE1hu+8LXRYpFQTijQntf/iEreMUi33NPK15opVy4706IhQgSYlgwrgVRHU=",
      "albl": [
        "Girls",
        "Original"
      ],
      "norl": [
        "Blush"
      ],
      "spel": [
        "Girls Hair Silver",
        "Girls Hair White",
        "Girls Hoodie",
        "Girls Short Hair",
        "Girls Long Hair",
        "Girls Cute Cool",
        "Girls Eyes Blue"
      ],
      "i_top": 0,
      "i_newest": 0,
      "i_sgg": 0,
      "h_img": 1101,
      "w_img": 775,
      "date_img_modified": 1645540912764,
      "file_size": "89.72 Kb"
    },
    {
      "id_img": "Original_683456_crop2608_-566702876",
      "lik": "UTb0sGqADnbLiHq9qhRMRkSRiLND0Tk7ctN8tpraiidXsmJZ5OZPfnWhjx2jbr71d4hUIIUoKV457Lbb2/yFKJVy4706IhQgSYlgwrgVRHU=",
      "thub": "UTb0sGqADnbLiHq9qhRMRkSRiLND0Tk7ctN8tpraiidXsmJZ5OZPfnWhjx2jbr71mW4oNv3nydSS30os8XwV4pVy4706IhQgSYlgwrgVRHU=",
      "albl": [
        "Girls",
        "Original"
      ],
      "norl": [
        "Monster",
        "Braid",
        "Magic"
      ],
      "spel": [
        "Girls Hair Black",
        "Girls Dark",
        "Girls Horns",
        "Dark Black",
        "Girls Eyes Red",
        "Girls Long Hair",
        "Girls Cute Cool",
        "Girls Tie Bows"
      ],
      "i_top": 0,
      "i_newest": 0,
      "i_sgg": 0,
      "h_img": 1200,
      "w_img": 844,
      "date_img_modified": 1645540912453,
      "file_size": "110.96 Kb"
    }
  ]
}